{"Version":{"tml_elements":["nVersionMajor","nVersionMinor"],"nVersionMajor":2,"nVersionMinor":0},"tml_elements":["Version","Citation","Compound","PureOrMixtureData"],"PureOrMixtureData":[{"Constraint":[{"tml_elements":["nConstraintNumber","ConstraintID","ConstraintPhaseID","nConstraintValue","nConstrDigits"],"nConstraintValue":101,"ConstraintPhaseID":{"tml_elements":["eConstraintPhase"],"eConstraintPhase":"Liquid"},"nConstraintNumber":1,"nConstrDigits":3,"ConstraintID":{"tml_elements":["ConstraintType"],"ConstraintType":{"ePressure":"Pressure, kPa","tml_elements":["ePressure"]}}}],"sContributor":"TRC","Variable":[{"tml_elements":["nVarNumber","VariableID","VarPhaseID"],"nVarNumber":1,"VarPhaseID":{"tml_elements":["eVarPhase"],"eVarPhase":"Liquid"},"VariableID":{"VariableType":{"eTemperature":"Temperature, K","tml_elements":["eTemperature"]},"tml_elements":["VariableType"]}}],"tml_elements":["nPureOrMixtureDataNumber","Component","eExpPurpose","sCompiler","sContributor","dateDateAdded","Property","PhaseID","Constraint","Variable","NumValues"],"PhaseID":[{"tml_elements":["ePhase"],"ePhase":"Liquid"},{"RegNum":{"nOrgNum":1,"tml_elements":["nOrgNum"]},"tml_elements":["ePhase","RegNum"],"ePhase":"Crystal"}],"Component":[{"RegNum":{"tml_elements":["nOrgNum"],"nOrgNum":7},"nSampleNm":1,"tml_elements":["RegNum","nSampleNm"]},{"RegNum":{"nOrgNum":1,"tml_elements":["nOrgNum"]},"nSampleNm":1,"tml_elements":["RegNum","nSampleNm"]}],"dateDateAdded":"9/27/2010","nPureOrMixtureDataNumber":1,"sCompiler":"GPC","NumValues":[{"VariableValue":[{"nVarValue":293.15,"nVarNumber":1,"tml_elements":["nVarNumber","nVarValue","nVarDigits"],"nVarDigits":5}],"PropertyValue":[{"nPropValue":5.066e-05,"CombinedUncertainty":{"nCombUncertAssessNum":1,"nCombExpandUncertValue":4.1e-07,"tml_elements":["nCombUncertAssessNum","nCombExpandUncertValue"]},"nPropDigits":4,"nPropNumber":1,"tml_elements":["nPropNumber","nPropValue","nPropDigits","CombinedUncertainty"]}],"tml_elements":["VariableValue","PropertyValue"]},{"PropertyValue":[{"nPropValue":6.302e-05,"CombinedUncertainty":{"nCombExpandUncertValue":4.9e-07,"tml_elements":["nCombUncertAssessNum","nCombExpandUncertValue"],"nCombUncertAssessNum":1},"nPropNumber":1,"nPropDigits":4,"tml_elements":["nPropNumber","nPropValue","nPropDigits","CombinedUncertainty"]}],"tml_elements":["VariableValue","PropertyValue"],"VariableValue":[{"nVarValue":298.15,"nVarNumber":1,"tml_elements":["nVarNumber","nVarValue","nVarDigits"],"nVarDigits":5}]},{"VariableValue":[{"nVarValue":303.15,"nVarNumber":1,"tml_elements":["nVarNumber","nVarValue","nVarDigits"],"nVarDigits":5}],"PropertyValue":[{"CombinedUncertainty":{"nCombUncertAssessNum":1,"nCombExpandUncertValue":6e-07,"tml_elements":["nCombUncertAssessNum","nCombExpandUncertValue"]},"nPropValue":7.78e-05,"tml_elements":["nPropNumber","nPropValue","nPropDigits","CombinedUncertainty"],"nPropDigits":4,"nPropNumber":1}],"tml_elements":["VariableValue","PropertyValue"]},{"VariableValue":[{"nVarValue":308.15,"tml_elements":["nVarNumber","nVarValue","nVarDigits"],"nVarDigits":5,"nVarNumber":1}],"tml_elements":["VariableValue","PropertyValue"],"PropertyValue":[{"tml_elements":["nPropNumber","nPropValue","nPropDigits","CombinedUncertainty"],"nPropDigits":4,"nPropNumber":1,"nPropValue":9.507e-05,"CombinedUncertainty":{"nCombExpandUncertValue":7.3e-07,"tml_elements":["nCombUncertAssessNum","nCombExpandUncertValue"],"nCombUncertAssessNum":1}}]},{"PropertyValue":[{"nPropValue":0.0001177,"CombinedUncertainty":{"nCombExpandUncertValue":9e-07,"tml_elements":["nCombUncertAssessNum","nCombExpandUncertValue"],"nCombUncertAssessNum":1},"nPropDigits":4,"nPropNumber":1,"tml_elements":["nPropNumber","nPropValue","nPropDigits","CombinedUncertainty"]}],"tml_elements":["VariableValue","PropertyValue"],"VariableValue":[{"nVarNumber":1,"nVarDigits":5,"tml_elements":["nVarNumber","nVarValue","nVarDigits"],"nVarValue":313.15}]},{"VariableValue":[{"nVarNumber":1,"tml_elements":["nVarNumber","nVarValue","nVarDigits"],"nVarDigits":5,"nVarValue":318.15}],"tml_elements":["VariableValue","PropertyValue"],"PropertyValue":[{"nPropValue":0.0001423,"CombinedUncertainty":{"tml_elements":["nCombUncertAssessNum","nCombExpandUncertValue"],"nCombExpandUncertValue":1.1e-06,"nCombUncertAssessNum":1},"tml_elements":["nPropNumber","nPropValue","nPropDigits","CombinedUncertainty"],"nPropDigits":4,"nPropNumber":1}]},{"VariableValue":[{"nVarValue":323.15,"nVarNumber":1,"nVarDigits":5,"tml_elements":["nVarNumber","nVarValue","nVarDigits"]}],"tml_elements":["VariableValue","PropertyValue"],"PropertyValue":[{"tml_elements":["nPropNumber","nPropValue","nPropDigits","CombinedUncertainty"],"nPropDigits":4,"nPropNumber":1,"CombinedUncertainty":{"tml_elements":["nCombUncertAssessNum","nCombExpandUncertValue"],"nCombExpandUncertValue":1.3e-06,"nCombUncertAssessNum":1},"nPropValue":0.0001752}]},{"PropertyValue":[{"CombinedUncertainty":{"tml_elements":["nCombUncertAssessNum","nCombExpandUncertValue"],"nCombExpandUncertValue":1.6e-06,"nCombUncertAssessNum":1},"nPropValue":0.0002126,"tml_elements":["nPropNumber","nPropValue","nPropDigits","CombinedUncertainty"],"nPropDigits":4,"nPropNumber":1}],"tml_elements":["VariableValue","PropertyValue"],"VariableValue":[{"nVarNumber":1,"tml_elements":["nVarNumber","nVarValue","nVarDigits"],"nVarDigits":5,"nVarValue":328.15}]},{"VariableValue":[{"tml_elements":["nVarNumber","nVarValue","nVarDigits"],"nVarDigits":5,"nVarNumber":1,"nVarValue":333.15}],"tml_elements":["VariableValue","PropertyValue"],"PropertyValue":[{"nPropNumber":1,"nPropDigits":4,"tml_elements":["nPropNumber","nPropValue","nPropDigits","CombinedUncertainty"],"nPropValue":0.0002548,"CombinedUncertainty":{"nCombExpandUncertValue":1.8e-06,"tml_elements":["nCombUncertAssessNum","nCombExpandUncertValue"],"nCombUncertAssessNum":1}}]}],"eExpPurpose":"Principal objective of the work","Property":[{"PropPhaseID":{"ePropPhase":"Liquid","tml_elements":["ePropPhase"]},"nPropNumber":1,"ePresentation":"Direct value, X","tml_elements":["nPropNumber","Property-MethodID","PropPhaseID","ePresentation","CombinedUncertainty"],"CombinedUncertainty":{"nCombUncertAssessNum":1,"sCombUncertEvaluator":"Data file compiler","tml_elements":["nCombUncertAssessNum","sCombUncertEvaluator","eCombUncertEvalMethod","nCombUncertLevOfConfid"],"eCombUncertEvalMethod":"Propagation of evaluated standard uncertainties","nCombUncertLevOfConfid":95},"Property-MethodID":{"tml_elements":["PropertyGroup","RegNum"],"PropertyGroup":{"CompositionAtPhaseEquilibrium":{"ePropName":"Mole fraction","sMethodName":"Static equilibrium method","tml_elements":["ePropName","sMethodName"]},"tml_elements":["CompositionAtPhaseEquilibrium"]},"RegNum":{"tml_elements":["nOrgNum"],"nOrgNum":1}}}]},{"Constraint":[{"nConstraintValue":101,"tml_elements":["nConstraintNumber","ConstraintID","ConstraintPhaseID","nConstraintValue","nConstrDigits"],"ConstraintPhaseID":{"eConstraintPhase":"Liquid","tml_elements":["eConstraintPhase"]},"nConstraintNumber":1,"nConstrDigits":3,"ConstraintID":{"ConstraintType":{"tml_elements":["ePressure"],"ePressure":"Pressure, kPa"},"tml_elements":["ConstraintType"]}}],"Variable":[{"VariableID":{"VariableType":{"eTemperature":"Temperature, K","tml_elements":["eTemperature"]},"tml_elements":["VariableType"]},"VarPhaseID":{"tml_elements":["eVarPhase"],"eVarPhase":"Liquid"},"nVarNumber":1,"tml_elements":["nVarNumber","VariableID","VarPhaseID"]}],"sContributor":"TRC","PhaseID":[{"tml_elements":["ePhase"],"ePhase":"Liquid"},{"ePhase":"Crystal","tml_elements":["ePhase","RegNum"],"RegNum":{"tml_elements":["nOrgNum"],"nOrgNum":2}}],"tml_elements":["nPureOrMixtureDataNumber","Component","eExpPurpose","sCompiler","sContributor","dateDateAdded","Property","PhaseID","Constraint","Variable","NumValues"],"Component":[{"tml_elements":["RegNum","nSampleNm"],"nSampleNm":1,"RegNum":{"tml_elements":["nOrgNum"],"nOrgNum":7}},{"tml_elements":["RegNum","nSampleNm"],"RegNum":{"nOrgNum":2,"tml_elements":["nOrgNum"]},"nSampleNm":1}],"sCompiler":"GPC","dateDateAdded":"9/27/2010","nPureOrMixtureDataNumber":2,"NumValues":[{"PropertyValue":[{"nPropValue":5.165e-05,"CombinedUncertainty":{"nCombExpandUncertValue":4.1e-07,"tml_elements":["nCombUncertAssessNum","nCombExpandUncertValue"],"nCombUncertAssessNum":1},"nPropNumber":1,"nPropDigits":4,"tml_elements":["nPropNumber","nPropValue","nPropDigits","CombinedUncertainty"]}],"tml_elements":["VariableValue","PropertyValue"],"VariableValue":[{"nVarNumber":1,"tml_elements":["nVarNumber","nVarValue","nVarDigits"],"nVarDigits":5,"nVarValue":293.15}]},{"VariableValue":[{"nVarValue":298.15,"nVarDigits":5,"tml_elements":["nVarNumber","nVarValue","nVarDigits"],"nVarNumber":1}],"tml_elements":["VariableValue","PropertyValue"],"PropertyValue":[{"CombinedUncertainty":{"tml_elements":["nCombUncertAssessNum","nCombExpandUncertValue"],"nCombExpandUncertValue":5.1e-07,"nCombUncertAssessNum":1},"nPropValue":6.622e-05,"tml_elements":["nPropNumber","nPropValue","nPropDigits","CombinedUncertainty"],"nPropNumber":1,"nPropDigits":4}]},{"tml_elements":["VariableValue","PropertyValue"],"PropertyValue":[{"nPropValue":8.542e-05,"CombinedUncertainty":{"nCombExpandUncertValue":6.4e-07,"tml_elements":["nCombUncertAssessNum","nCombExpandUncertValue"],"nCombUncertAssessNum":1},"nPropDigits":4,"nPropNumber":1,"tml_elements":["nPropNumber","nPropValue","nPropDigits","CombinedUncertainty"]}],"VariableValue":[{"nVarNumber":1,"nVarDigits":5,"tml_elements":["nVarNumber","nVarValue","nVarDigits"],"nVarValue":303.15}]},{"VariableValue":[{"nVarNumber":1,"nVarDigits":5,"tml_elements":["nVarNumber","nVarValue","nVarDigits"],"nVarValue":308.15}],"tml_elements":["VariableValue","PropertyValue"],"PropertyValue":[{"nPropValue":0.0001083,"CombinedUncertainty":{"nCombUncertAssessNum":1,"nCombExpandUncertValue":8e-07,"tml_elements":["nCombUncertAssessNum","nCombExpandUncertValue"]},"tml_elements":["nPropNumber","nPropValue","nPropDigits","CombinedUncertainty"],"nPropDigits":4,"nPropNumber":1}]},{"tml_elements":["VariableValue","PropertyValue"],"PropertyValue":[{"CombinedUncertainty":{"nCombUncertAssessNum":1,"nCombExpandUncertValue":1.1e-06,"tml_elements":["nCombUncertAssessNum","nCombExpandUncertValue"]},"nPropValue":0.0001405,"nPropNumber":1,"nPropDigits":4,"tml_elements":["nPropNumber","nPropValue","nPropDigits","CombinedUncertainty"]}],"VariableValue":[{"nVarDigits":5,"tml_elements":["nVarNumber","nVarValue","nVarDigits"],"nVarNumber":1,"nVarValue":313.15}]},{"VariableValue":[{"nVarValue":318.15,"tml_elements":["nVarNumber","nVarValue","nVarDigits"],"nVarDigits":5,"nVarNumber":1}],"tml_elements":["VariableValue","PropertyValue"],"PropertyValue":[{"tml_elements":["nPropNumber","nPropValue","nPropDigits","CombinedUncertainty"],"nPropNumber":1,"nPropDigits":4,"CombinedUncertainty":{"tml_elements":["nCombUncertAssessNum","nCombExpandUncertValue"],"nCombExpandUncertValue":1.3e-06,"nCombUncertAssessNum":1},"nPropValue":0.0001773}]},{"PropertyValue":[{"CombinedUncertainty":{"tml_elements":["nCombUncertAssessNum","nCombExpandUncertValue"],"nCombExpandUncertValue":1.7e-06,"nCombUncertAssessNum":1},"nPropValue":0.0002236,"nPropDigits":4,"nPropNumber":1,"tml_elements":["nPropNumber","nPropValue","nPropDigits","CombinedUncertainty"]}],"tml_elements":["VariableValue","PropertyValue"],"VariableValue":[{"nVarValue":323.15,"tml_elements":["nVarNumber","nVarValue","nVarDigits"],"nVarDigits":5,"nVarNumber":1}]},{"VariableValue":[{"nVarValue":328.15,"tml_elements":["nVarNumber","nVarValue","nVarDigits"],"nVarDigits":5,"nVarNumber":1}],"tml_elements":["VariableValue","PropertyValue"],"PropertyValue":[{"nPropNumber":1,"nPropDigits":4,"tml_elements":["nPropNumber","nPropValue","nPropDigits","CombinedUncertainty"],"CombinedUncertainty":{"tml_elements":["nCombUncertAssessNum","nCombExpandUncertValue"],"nCombExpandUncertValue":2.1e-06,"nCombUncertAssessNum":1},"nPropValue":0.0002845}]},{"VariableValue":[{"nVarNumber":1,"nVarDigits":5,"tml_elements":["nVarNumber","nVarValue","nVarDigits"],"nVarValue":333.15}],"tml_elements":["VariableValue","PropertyValue"],"PropertyValue":[{"nPropValue":0.0003518,"CombinedUncertainty":{"nCombExpandUncertValue":2.4e-06,"tml_elements":["nCombUncertAssessNum","nCombExpandUncertValue"],"nCombUncertAssessNum":1},"tml_elements":["nPropNumber","nPropValue","nPropDigits","CombinedUncertainty"],"nPropDigits":4,"nPropNumber":1}]}],"eExpPurpose":"Principal objective of the work","Property":[{"nPropNumber":1,"PropPhaseID":{"tml_elements":["ePropPhase"],"ePropPhase":"Liquid"},"Property-MethodID":{"tml_elements":["PropertyGroup","RegNum"],"PropertyGroup":{"CompositionAtPhaseEquilibrium":{"tml_elements":["ePropName","sMethodName"],"sMethodName":"Static equilibrium method","ePropName":"Mole fraction"},"tml_elements":["CompositionAtPhaseEquilibrium"]},"RegNum":{"nOrgNum":2,"tml_elements":["nOrgNum"]}},"tml_elements":["nPropNumber","Property-MethodID","PropPhaseID","ePresentation","CombinedUncertainty"],"ePresentation":"Direct value, X","CombinedUncertainty":{"tml_elements":["nCombUncertAssessNum","sCombUncertEvaluator","eCombUncertEvalMethod","nCombUncertLevOfConfid"],"eCombUncertEvalMethod":"Propagation of evaluated standard uncertainties","nCombUncertLevOfConfid":95,"nCombUncertAssessNum":1,"sCombUncertEvaluator":"Data file compiler"}}]},{"PhaseID":[{"ePhase":"Liquid","tml_elements":["ePhase"]},{"tml_elements":["ePhase","RegNum"],"ePhase":"Crystal","RegNum":{"nOrgNum":3,"tml_elements":["nOrgNum"]}}],"tml_elements":["nPureOrMixtureDataNumber","Component","eExpPurpose","sCompiler","sContributor","dateDateAdded","Property","PhaseID","Constraint","Variable","NumValues"],"Component":[{"tml_elements":["RegNum","nSampleNm"],"RegNum":{"tml_elements":["nOrgNum"],"nOrgNum":7},"nSampleNm":1},{"nSampleNm":1,"RegNum":{"tml_elements":["nOrgNum"],"nOrgNum":3},"tml_elements":["RegNum","nSampleNm"]}],"Constraint":[{"ConstraintPhaseID":{"tml_elements":["eConstraintPhase"],"eConstraintPhase":"Liquid"},"nConstrDigits":3,"nConstraintNumber":1,"tml_elements":["nConstraintNumber","ConstraintID","ConstraintPhaseID","nConstraintValue","nConstrDigits"],"ConstraintID":{"ConstraintType":{"ePressure":"Pressure, kPa","tml_elements":["ePressure"]},"tml_elements":["ConstraintType"]},"nConstraintValue":101}],"Variable":[{"tml_elements":["nVarNumber","VariableID","VarPhaseID"],"nVarNumber":1,"VarPhaseID":{"tml_elements":["eVarPhase"],"eVarPhase":"Liquid"},"VariableID":{"VariableType":{"tml_elements":["eTemperature"],"eTemperature":"Temperature, K"},"tml_elements":["VariableType"]}}],"sContributor":"TRC","eExpPurpose":"Principal objective of the work","Property":[{"tml_elements":["nPropNumber","Property-MethodID","PropPhaseID","ePresentation","CombinedUncertainty"],"ePresentation":"Direct value, X","nPropNumber":1,"PropPhaseID":{"ePropPhase":"Liquid","tml_elements":["ePropPhase"]},"CombinedUncertainty":{"nCombUncertAssessNum":1,"sCombUncertEvaluator":"Data file compiler","tml_elements":["nCombUncertAssessNum","sCombUncertEvaluator","eCombUncertEvalMethod","nCombUncertLevOfConfid"],"nCombUncertLevOfConfid":95,"eCombUncertEvalMethod":"Propagation of evaluated standard uncertainties"},"Property-MethodID":{"PropertyGroup":{"tml_elements":["CompositionAtPhaseEquilibrium"],"CompositionAtPhaseEquilibrium":{"tml_elements":["ePropName","sMethodName"],"ePropName":"Mole fraction","sMethodName":"Static equilibrium method"}},"tml_elements":["PropertyGroup","RegNum"],"RegNum":{"nOrgNum":3,"tml_elements":["nOrgNum"]}}}],"sCompiler":"GPC","nPureOrMixtureDataNumber":3,"dateDateAdded":"9/27/2010","NumValues":[{"PropertyValue":[{"nPropDigits":4,"nPropNumber":1,"tml_elements":["nPropNumber","nPropValue","nPropDigits","CombinedUncertainty"],"nPropValue":2.168e-06,"CombinedUncertainty":{"nCombExpandUncertValue":2e-08,"tml_elements":["nCombUncertAssessNum","nCombExpandUncertValue"],"nCombUncertAssessNum":1}}],"tml_elements":["VariableValue","PropertyValue"],"VariableValue":[{"nVarValue":293.15,"nVarNumber":1,"nVarDigits":5,"tml_elements":["nVarNumber","nVarValue","nVarDigits"]}]},{"tml_elements":["VariableValue","PropertyValue"],"PropertyValue":[{"nPropValue":2.758e-06,"CombinedUncertainty":{"nCombUncertAssessNum":1,"tml_elements":["nCombUncertAssessNum","nCombExpandUncertValue"],"nCombExpandUncertValue":2.3e-08},"tml_elements":["nPropNumber","nPropValue","nPropDigits","CombinedUncertainty"],"nPropNumber":1,"nPropDigits":4}],"VariableValue":[{"nVarNumber":1,"nVarDigits":5,"tml_elements":["nVarNumber","nVarValue","nVarDigits"],"nVarValue":298.15}]},{"VariableValue":[{"nVarValue":303.15,"nVarDigits":5,"tml_elements":["nVarNumber","nVarValue","nVarDigits"],"nVarNumber":1}],"PropertyValue":[{"tml_elements":["nPropNumber","nPropValue","nPropDigits","CombinedUncertainty"],"nPropNumber":1,"nPropDigits":4,"CombinedUncertainty":{"tml_elements":["nCombUncertAssessNum","nCombExpandUncertValue"],"nCombExpandUncertValue":2.9e-08,"nCombUncertAssessNum":1},"nPropValue":3.554e-06}],"tml_elements":["VariableValue","PropertyValue"]},{"tml_elements":["VariableValue","PropertyValue"],"PropertyValue":[{"CombinedUncertainty":{"nCombExpandUncertValue":3.7e-08,"tml_elements":["nCombUncertAssessNum","nCombExpandUncertValue"],"nCombUncertAssessNum":1},"nPropValue":4.582e-06,"nPropNumber":1,"nPropDigits":4,"tml_elements":["nPropNumber","nPropValue","nPropDigits","CombinedUncertainty"]}],"VariableValue":[{"nVarValue":308.15,"nVarDigits":5,"tml_elements":["nVarNumber","nVarValue","nVarDigits"],"nVarNumber":1}]},{"tml_elements":["VariableValue","PropertyValue"],"PropertyValue":[{"nPropDigits":4,"nPropNumber":1,"tml_elements":["nPropNumber","nPropValue","nPropDigits","CombinedUncertainty"],"nPropValue":5.883e-06,"CombinedUncertainty":{"nCombUncertAssessNum":1,"tml_elements":["nCombUncertAssessNum","nCombExpandUncertValue"],"nCombExpandUncertValue":4.8e-08}}],"VariableValue":[{"nVarValue":313.15,"nVarNumber":1,"nVarDigits":5,"tml_elements":["nVarNumber","nVarValue","nVarDigits"]}]},{"VariableValue":[{"tml_elements":["nVarNumber","nVarValue","nVarDigits"],"nVarDigits":5,"nVarNumber":1,"nVarValue":318.15}],"PropertyValue":[{"nPropNumber":1,"nPropDigits":4,"tml_elements":["nPropNumber","nPropValue","nPropDigits","CombinedUncertainty"],"nPropValue":7.631e-06,"CombinedUncertainty":{"tml_elements":["nCombUncertAssessNum","nCombExpandUncertValue"],"nCombExpandUncertValue":6.3e-08,"nCombUncertAssessNum":1}}],"tml_elements":["VariableValue","PropertyValue"]},{"PropertyValue":[{"nPropValue":9.914e-06,"CombinedUncertainty":{"nCombUncertAssessNum":1,"nCombExpandUncertValue":8.2e-08,"tml_elements":["nCombUncertAssessNum","nCombExpandUncertValue"]},"tml_elements":["nPropNumber","nPropValue","nPropDigits","CombinedUncertainty"],"nPropDigits":4,"nPropNumber":1}],"tml_elements":["VariableValue","PropertyValue"],"VariableValue":[{"tml_elements":["nVarNumber","nVarValue","nVarDigits"],"nVarDigits":5,"nVarNumber":1,"nVarValue":323.15}]},{"PropertyValue":[{"tml_elements":["nPropNumber","nPropValue","nPropDigits","CombinedUncertainty"],"nPropNumber":1,"nPropDigits":4,"nPropValue":1.296e-05,"CombinedUncertainty":{"nCombExpandUncertValue":1.1e-07,"tml_elements":["nCombUncertAssessNum","nCombExpandUncertValue"],"nCombUncertAssessNum":1}}],"tml_elements":["VariableValue","PropertyValue"],"VariableValue":[{"nVarValue":328.15,"tml_elements":["nVarNumber","nVarValue","nVarDigits"],"nVarDigits":5,"nVarNumber":1}]},{"tml_elements":["VariableValue","PropertyValue"],"PropertyValue":[{"tml_elements":["nPropNumber","nPropValue","nPropDigits","CombinedUncertainty"],"nPropNumber":1,"nPropDigits":4,"nPropValue":1.682e-05,"CombinedUncertainty":{"nCombExpandUncertValue":1.3e-07,"tml_elements":["nCombUncertAssessNum","nCombExpandUncertValue"],"nCombUncertAssessNum":1}}],"VariableValue":[{"nVarValue":333.15,"nVarDigits":5,"tml_elements":["nVarNumber","nVarValue","nVarDigits"],"nVarNumber":1}]}]},{"NumValues":[{"tml_elements":["VariableValue","PropertyValue"],"PropertyValue":[{"tml_elements":["nPropNumber","nPropValue","nPropDigits","CombinedUncertainty"],"nPropNumber":1,"nPropDigits":4,"CombinedUncertainty":{"nCombExpandUncertValue":1.06e-08,"tml_elements":["nCombUncertAssessNum","nCombExpandUncertValue"],"nCombUncertAssessNum":1},"nPropValue":2.559e-07}],"VariableValue":[{"nVarNumber":1,"nVarDigits":5,"tml_elements":["nVarNumber","nVarValue","nVarDigits"],"nVarValue":293.15}]},{"VariableValue":[{"nVarValue":298.15,"nVarDigits":5,"tml_elements":["nVarNumber","nVarValue","nVarDigits"],"nVarNumber":1}],"PropertyValue":[{"nPropNumber":1,"nPropDigits":4,"tml_elements":["nPropNumber","nPropValue","nPropDigits","CombinedUncertainty"],"CombinedUncertainty":{"nCombExpandUncertValue":1.09e-08,"tml_elements":["nCombUncertAssessNum","nCombExpandUncertValue"],"nCombUncertAssessNum":1},"nPropValue":4.094e-07}],"tml_elements":["VariableValue","PropertyValue"]},{"tml_elements":["VariableValue","PropertyValue"],"PropertyValue":[{"tml_elements":["nPropNumber","nPropValue","nPropDigits","CombinedUncertainty"],"nPropDigits":4,"nPropNumber":1,"nPropValue":6.354e-07,"CombinedUncertainty":{"nCombUncertAssessNum":1,"nCombExpandUncertValue":1.19e-08,"tml_elements":["nCombUncertAssessNum","nCombExpandUncertValue"]}}],"VariableValue":[{"nVarNumber":1,"tml_elements":["nVarNumber","nVarValue","nVarDigits"],"nVarDigits":5,"nVarValue":303.15}]},{"tml_elements":["VariableValue","PropertyValue"],"PropertyValue":[{"tml_elements":["nPropNumber","nPropValue","nPropDigits","CombinedUncertainty"],"nPropNumber":1,"nPropDigits":4,"nPropValue":9.551e-07,"CombinedUncertainty":{"nCombExpandUncertValue":1.35e-08,"tml_elements":["nCombUncertAssessNum","nCombExpandUncertValue"],"nCombUncertAssessNum":1}}],"VariableValue":[{"nVarValue":308.15,"nVarNumber":1,"nVarDigits":5,"tml_elements":["nVarNumber","nVarValue","nVarDigits"]}]},{"VariableValue":[{"tml_elements":["nVarNumber","nVarValue","nVarDigits"],"nVarDigits":5,"nVarNumber":1,"nVarValue":313.15}],"tml_elements":["VariableValue","PropertyValue"],"PropertyValue":[{"tml_elements":["nPropNumber","nPropValue","nPropDigits","CombinedUncertainty"],"nPropNumber":1,"nPropDigits":4,"nPropValue":1.384e-06,"CombinedUncertainty":{"nCombUncertAssessNum":1,"tml_elements":["nCombUncertAssessNum","nCombExpandUncertValue"],"nCombExpandUncertValue":1.6e-08}}]},{"tml_elements":["VariableValue","PropertyValue"],"PropertyValue":[{"nPropValue":1.962e-06,"CombinedUncertainty":{"tml_elements":["nCombUncertAssessNum","nCombExpandUncertValue"],"nCombExpandUncertValue":2e-08,"nCombUncertAssessNum":1},"tml_elements":["nPropNumber","nPropValue","nPropDigits","CombinedUncertainty"],"nPropNumber":1,"nPropDigits":4}],"VariableValue":[{"nVarNumber":1,"tml_elements":["nVarNumber","nVarValue","nVarDigits"],"nVarDigits":5,"nVarValue":318.15}]},{"PropertyValue":[{"nPropValue":2.682e-06,"CombinedUncertainty":{"nCombExpandUncertValue":2.4e-08,"tml_elements":["nCombUncertAssessNum","nCombExpandUncertValue"],"nCombUncertAssessNum":1},"tml_elements":["nPropNumber","nPropValue","nPropDigits","CombinedUncertainty"],"nPropDigits":4,"nPropNumber":1}],"tml_elements":["VariableValue","PropertyValue"],"VariableValue":[{"nVarValue":323.15,"nVarNumber":1,"tml_elements":["nVarNumber","nVarValue","nVarDigits"],"nVarDigits":5}]},{"tml_elements":["VariableValue","PropertyValue"],"PropertyValue":[{"CombinedUncertainty":{"nCombExpandUncertValue":3e-08,"tml_elements":["nCombUncertAssessNum","nCombExpandUncertValue"],"nCombUncertAssessNum":1},"nPropValue":3.621e-06,"tml_elements":["nPropNumber","nPropValue","nPropDigits","CombinedUncertainty"],"nPropNumber":1,"nPropDigits":4}],"VariableValue":[{"nVarValue":328.15,"nVarNumber":1,"tml_elements":["nVarNumber","nVarValue","nVarDigits"],"nVarDigits":5}]},{"VariableValue":[{"nVarDigits":5,"tml_elements":["nVarNumber","nVarValue","nVarDigits"],"nVarNumber":1,"nVarValue":333.15}],"tml_elements":["VariableValue","PropertyValue"],"PropertyValue":[{"nPropValue":4.732e-06,"CombinedUncertainty":{"tml_elements":["nCombUncertAssessNum","nCombExpandUncertValue"],"nCombExpandUncertValue":3.6e-08,"nCombUncertAssessNum":1},"nPropDigits":4,"nPropNumber":1,"tml_elements":["nPropNumber","nPropValue","nPropDigits","CombinedUncertainty"]}]}],"nPureOrMixtureDataNumber":4,"dateDateAdded":"9/27/2010","sCompiler":"GPC","Property":[{"Property-MethodID":{"tml_elements":["PropertyGroup","RegNum"],"PropertyGroup":{"CompositionAtPhaseEquilibrium":{"tml_elements":["ePropName","sMethodName"],"ePropName":"Mole fraction","sMethodName":"Static equilibrium method"},"tml_elements":["CompositionAtPhaseEquilibrium"]},"RegNum":{"nOrgNum":4,"tml_elements":["nOrgNum"]}},"PropPhaseID":{"tml_elements":["ePropPhase"],"ePropPhase":"Liquid"},"nPropNumber":1,"ePresentation":"Direct value, X","tml_elements":["nPropNumber","Property-MethodID","PropPhaseID","ePresentation","CombinedUncertainty"],"CombinedUncertainty":{"tml_elements":["nCombUncertAssessNum","sCombUncertEvaluator","eCombUncertEvalMethod","nCombUncertLevOfConfid"],"eCombUncertEvalMethod":"Propagation of evaluated standard uncertainties","nCombUncertLevOfConfid":95,"nCombUncertAssessNum":1,"sCombUncertEvaluator":"Data file compiler"}}],"eExpPurpose":"Principal objective of the work","Variable":[{"tml_elements":["nVarNumber","VariableID","VarPhaseID"],"VarPhaseID":{"tml_elements":["eVarPhase"],"eVarPhase":"Liquid"},"nVarNumber":1,"VariableID":{"tml_elements":["VariableType"],"VariableType":{"eTemperature":"Temperature, K","tml_elements":["eTemperature"]}}}],"Component":[{"nSampleNm":1,"RegNum":{"tml_elements":["nOrgNum"],"nOrgNum":7},"tml_elements":["RegNum","nSampleNm"]},{"tml_elements":["RegNum","nSampleNm"],"RegNum":{"nOrgNum":4,"tml_elements":["nOrgNum"]},"nSampleNm":1}],"sContributor":"TRC","Constraint":[{"nConstraintValue":101,"tml_elements":["nConstraintNumber","ConstraintID","ConstraintPhaseID","nConstraintValue","nConstrDigits"],"ConstraintPhaseID":{"eConstraintPhase":"Liquid","tml_elements":["eConstraintPhase"]},"ConstraintID":{"ConstraintType":{"tml_elements":["ePressure"],"ePressure":"Pressure, kPa"},"tml_elements":["ConstraintType"]},"nConstraintNumber":1,"nConstrDigits":3}],"tml_elements":["nPureOrMixtureDataNumber","Component","eExpPurpose","sCompiler","sContributor","dateDateAdded","Property","PhaseID","Constraint","Variable","NumValues"],"PhaseID":[{"ePhase":"Liquid","tml_elements":["ePhase"]},{"ePhase":"Crystal","tml_elements":["ePhase","RegNum"],"RegNum":{"nOrgNum":4,"tml_elements":["nOrgNum"]}}]},{"Component":[{"tml_elements":["RegNum","nSampleNm"],"nSampleNm":1,"RegNum":{"tml_elements":["nOrgNum"],"nOrgNum":7}},{"RegNum":{"nOrgNum":5,"tml_elements":["nOrgNum"]},"nSampleNm":1,"tml_elements":["RegNum","nSampleNm"]}],"Variable":[{"tml_elements":["nVarNumber","VariableID","VarPhaseID"],"VarPhaseID":{"eVarPhase":"Liquid","tml_elements":["eVarPhase"]},"nVarNumber":1,"VariableID":{"VariableType":{"tml_elements":["eTemperature"],"eTemperature":"Temperature, K"},"tml_elements":["VariableType"]}}],"Property":[{"ePresentation":"Direct value, X","tml_elements":["nPropNumber","Property-MethodID","PropPhaseID","ePresentation","CombinedUncertainty"],"PropPhaseID":{"tml_elements":["ePropPhase"],"ePropPhase":"Liquid"},"Property-MethodID":{"RegNum":{"nOrgNum":5,"tml_elements":["nOrgNum"]},"PropertyGroup":{"CompositionAtPhaseEquilibrium":{"ePropName":"Mole fraction","sMethodName":"Static equilibrium method","tml_elements":["ePropName","sMethodName"]},"tml_elements":["CompositionAtPhaseEquilibrium"]},"tml_elements":["PropertyGroup","RegNum"]},"nPropNumber":1,"CombinedUncertainty":{"nCombUncertAssessNum":1,"sCombUncertEvaluator":"Data file compiler","tml_elements":["nCombUncertAssessNum","sCombUncertEvaluator","eCombUncertEvalMethod","nCombUncertLevOfConfid"],"eCombUncertEvalMethod":"Propagation of evaluated standard uncertainties","nCombUncertLevOfConfid":95}}],"eExpPurpose":"Principal objective of the work","nPureOrMixtureDataNumber":5,"dateDateAdded":"9/27/2010","sCompiler":"GPC","NumValues":[{"VariableValue":[{"tml_elements":["nVarNumber","nVarValue","nVarDigits"],"nVarDigits":5,"nVarNumber":1,"nVarValue":293.15}],"PropertyValue":[{"nPropValue":5.481e-07,"CombinedUncertainty":{"tml_elements":["nCombUncertAssessNum","nCombExpandUncertValue"],"nCombExpandUncertValue":1.33e-08,"nCombUncertAssessNum":1},"nPropNumber":1,"nPropDigits":4,"tml_elements":["nPropNumber","nPropValue","nPropDigits","CombinedUncertainty"]}],"tml_elements":["VariableValue","PropertyValue"]},{"tml_elements":["VariableValue","PropertyValue"],"PropertyValue":[{"nPropValue":9.63e-07,"CombinedUncertainty":{"nCombUncertAssessNum":1,"tml_elements":["nCombUncertAssessNum","nCombExpandUncertValue"],"nCombExpandUncertValue":1.59e-08},"tml_elements":["nPropNumber","nPropValue","nPropDigits","CombinedUncertainty"],"nPropNumber":1,"nPropDigits":4}],"VariableValue":[{"nVarDigits":5,"tml_elements":["nVarNumber","nVarValue","nVarDigits"],"nVarNumber":1,"nVarValue":298.15}]},{"PropertyValue":[{"tml_elements":["nPropNumber","nPropValue","nPropDigits","CombinedUncertainty"],"nPropDigits":4,"nPropNumber":1,"CombinedUncertainty":{"nCombUncertAssessNum":1,"nCombExpandUncertValue":2.2e-08,"tml_elements":["nCombUncertAssessNum","nCombExpandUncertValue"]},"nPropValue":1.666e-06}],"tml_elements":["VariableValue","PropertyValue"],"VariableValue":[{"nVarValue":303.15,"nVarNumber":1,"tml_elements":["nVarNumber","nVarValue","nVarDigits"],"nVarDigits":5}]},{"tml_elements":["VariableValue","PropertyValue"],"PropertyValue":[{"nPropValue":2.71e-06,"CombinedUncertainty":{"nCombExpandUncertValue":3.2e-08,"tml_elements":["nCombUncertAssessNum","nCombExpandUncertValue"],"nCombUncertAssessNum":1},"tml_elements":["nPropNumber","nPropValue","nPropDigits","CombinedUncertainty"],"nPropNumber":1,"nPropDigits":4}],"VariableValue":[{"nVarValue":308.15,"tml_elements":["nVarNumber","nVarValue","nVarDigits"],"nVarDigits":5,"nVarNumber":1}]},{"tml_elements":["VariableValue","PropertyValue"],"PropertyValue":[{"nPropValue":4.346e-06,"CombinedUncertainty":{"nCombUncertAssessNum":1,"nCombExpandUncertValue":4.8e-08,"tml_elements":["nCombUncertAssessNum","nCombExpandUncertValue"]},"tml_elements":["nPropNumber","nPropValue","nPropDigits","CombinedUncertainty"],"nPropNumber":1,"nPropDigits":4}],"VariableValue":[{"nVarDigits":5,"tml_elements":["nVarNumber","nVarValue","nVarDigits"],"nVarNumber":1,"nVarValue":313.15}]},{"tml_elements":["VariableValue","PropertyValue"],"PropertyValue":[{"tml_elements":["nPropNumber","nPropValue","nPropDigits","CombinedUncertainty"],"nPropDigits":4,"nPropNumber":1,"CombinedUncertainty":{"nCombUncertAssessNum":1,"nCombExpandUncertValue":7.2e-08,"tml_elements":["nCombUncertAssessNum","nCombExpandUncertValue"]},"nPropValue":6.768e-06}],"VariableValue":[{"nVarNumber":1,"nVarDigits":5,"tml_elements":["nVarNumber","nVarValue","nVarDigits"],"nVarValue":318.15}]},{"tml_elements":["VariableValue","PropertyValue"],"PropertyValue":[{"tml_elements":["nPropNumber","nPropValue","nPropDigits","CombinedUncertainty"],"nPropNumber":1,"nPropDigits":4,"nPropValue":1.035e-05,"CombinedUncertainty":{"nCombExpandUncertValue":1e-07,"tml_elements":["nCombUncertAssessNum","nCombExpandUncertValue"],"nCombUncertAssessNum":1}}],"VariableValue":[{"nVarValue":323.15,"tml_elements":["nVarNumber","nVarValue","nVarDigits"],"nVarDigits":5,"nVarNumber":1}]},{"tml_elements":["VariableValue","PropertyValue"],"PropertyValue":[{"tml_elements":["nPropNumber","nPropValue","nPropDigits","CombinedUncertainty"],"nPropNumber":1,"nPropDigits":4,"CombinedUncertainty":{"nCombUncertAssessNum":1,"tml_elements":["nCombUncertAssessNum","nCombExpandUncertValue"],"nCombExpandUncertValue":1.5e-07},"nPropValue":1.522e-05}],"VariableValue":[{"nVarValue":328.15,"nVarNumber":1,"tml_elements":["nVarNumber","nVarValue","nVarDigits"],"nVarDigits":5}]},{"VariableValue":[{"nVarValue":333.15,"nVarDigits":5,"tml_elements":["nVarNumber","nVarValue","nVarDigits"],"nVarNumber":1}],"PropertyValue":[{"nPropValue":2.186e-05,"CombinedUncertainty":{"nCombUncertAssessNum":1,"tml_elements":["nCombUncertAssessNum","nCombExpandUncertValue"],"nCombExpandUncertValue":1.9e-07},"nPropDigits":4,"nPropNumber":1,"tml_elements":["nPropNumber","nPropValue","nPropDigits","CombinedUncertainty"]}],"tml_elements":["VariableValue","PropertyValue"]}],"tml_elements":["nPureOrMixtureDataNumber","Component","eExpPurpose","sCompiler","sContributor","dateDateAdded","Property","PhaseID","Constraint","Variable","NumValues"],"PhaseID":[{"ePhase":"Liquid","tml_elements":["ePhase"]},{"ePhase":"Crystal","tml_elements":["ePhase","RegNum"],"RegNum":{"nOrgNum":5,"tml_elements":["nOrgNum"]}}],"Constraint":[{"ConstraintID":{"ConstraintType":{"ePressure":"Pressure, kPa","tml_elements":["ePressure"]},"tml_elements":["ConstraintType"]},"nConstrDigits":3,"nConstraintNumber":1,"ConstraintPhaseID":{"tml_elements":["eConstraintPhase"],"eConstraintPhase":"Liquid"},"nConstraintValue":101,"tml_elements":["nConstraintNumber","ConstraintID","ConstraintPhaseID","nConstraintValue","nConstrDigits"]}],"sContributor":"TRC"},{"NumValues":[{"PropertyValue":[{"nPropValue":9.138e-07,"CombinedUncertainty":{"nCombUncertAssessNum":1,"tml_elements":["nCombUncertAssessNum","nCombExpandUncertValue"],"nCombExpandUncertValue":1.24e-08},"nPropDigits":4,"nPropNumber":1,"tml_elements":["nPropNumber","nPropValue","nPropDigits","CombinedUncertainty"]}],"tml_elements":["VariableValue","PropertyValue"],"VariableValue":[{"nVarValue":293.15,"nVarNumber":1,"tml_elements":["nVarNumber","nVarValue","nVarDigits"],"nVarDigits":5}]},{"VariableValue":[{"nVarValue":298.15,"nVarDigits":5,"tml_elements":["nVarNumber","nVarValue","nVarDigits"],"nVarNumber":1}],"PropertyValue":[{"nPropNumber":1,"nPropDigits":4,"tml_elements":["nPropNumber","nPropValue","nPropDigits","CombinedUncertainty"],"nPropValue":1.205e-06,"CombinedUncertainty":{"tml_elements":["nCombUncertAssessNum","nCombExpandUncertValue"],"nCombExpandUncertValue":1.3e-08,"nCombUncertAssessNum":1}}],"tml_elements":["VariableValue","PropertyValue"]},{"tml_elements":["VariableValue","PropertyValue"],"PropertyValue":[{"nPropDigits":4,"nPropNumber":1,"tml_elements":["nPropNumber","nPropValue","nPropDigits","CombinedUncertainty"],"CombinedUncertainty":{"nCombUncertAssessNum":1,"tml_elements":["nCombUncertAssessNum","nCombExpandUncertValue"],"nCombExpandUncertValue":1.5e-08},"nPropValue":1.569e-06}],"VariableValue":[{"tml_elements":["nVarNumber","nVarValue","nVarDigits"],"nVarDigits":5,"nVarNumber":1,"nVarValue":303.15}]},{"tml_elements":["VariableValue","PropertyValue"],"PropertyValue":[{"nPropValue":2.028e-06,"CombinedUncertainty":{"nCombExpandUncertValue":1.8e-08,"tml_elements":["nCombUncertAssessNum","nCombExpandUncertValue"],"nCombUncertAssessNum":1},"nPropNumber":1,"nPropDigits":4,"tml_elements":["nPropNumber","nPropValue","nPropDigits","CombinedUncertainty"]}],"VariableValue":[{"tml_elements":["nVarNumber","nVarValue","nVarDigits"],"nVarDigits":5,"nVarNumber":1,"nVarValue":308.15}]},{"tml_elements":["VariableValue","PropertyValue"],"PropertyValue":[{"CombinedUncertainty":{"nCombUncertAssessNum":1,"tml_elements":["nCombUncertAssessNum","nCombExpandUncertValue"],"nCombExpandUncertValue":2e-08},"nPropValue":2.602e-06,"nPropNumber":1,"nPropDigits":4,"tml_elements":["nPropNumber","nPropValue","nPropDigits","CombinedUncertainty"]}],"VariableValue":[{"nVarValue":313.15,"nVarNumber":1,"tml_elements":["nVarNumber","nVarValue","nVarDigits"],"nVarDigits":5}]},{"PropertyValue":[{"nPropDigits":4,"nPropNumber":1,"tml_elements":["nPropNumber","nPropValue","nPropDigits","CombinedUncertainty"],"nPropValue":3.249e-06,"CombinedUncertainty":{"tml_elements":["nCombUncertAssessNum","nCombExpandUncertValue"],"nCombExpandUncertValue":2.4e-08,"nCombUncertAssessNum":1}}],"tml_elements":["VariableValue","PropertyValue"],"VariableValue":[{"tml_elements":["nVarNumber","nVarValue","nVarDigits"],"nVarDigits":5,"nVarNumber":1,"nVarValue":318.15}]},{"VariableValue":[{"tml_elements":["nVarNumber","nVarValue","nVarDigits"],"nVarDigits":5,"nVarNumber":1,"nVarValue":323.15}],"PropertyValue":[{"CombinedUncertainty":{"nCombUncertAssessNum":1,"tml_elements":["nCombUncertAssessNum","nCombExpandUncertValue"],"nCombExpandUncertValue":2.8e-08},"nPropValue":4.049e-06,"tml_elements":["nPropNumber","nPropValue","nPropDigits","CombinedUncertainty"],"nPropNumber":1,"nPropDigits":4}],"tml_elements":["VariableValue","PropertyValue"]},{"tml_elements":["VariableValue","PropertyValue"],"PropertyValue":[{"CombinedUncertainty":{"nCombExpandUncertValue":3.3e-08,"tml_elements":["nCombUncertAssessNum","nCombExpandUncertValue"],"nCombUncertAssessNum":1},"nPropValue":4.969e-06,"tml_elements":["nPropNumber","nPropValue","nPropDigits","CombinedUncertainty"],"nPropNumber":1,"nPropDigits":4}],"VariableValue":[{"nVarDigits":5,"tml_elements":["nVarNumber","nVarValue","nVarDigits"],"nVarNumber":1,"nVarValue":328.15}]},{"tml_elements":["VariableValue","PropertyValue"],"PropertyValue":[{"nPropValue":6.021e-06,"CombinedUncertainty":{"nCombUncertAssessNum":1,"tml_elements":["nCombUncertAssessNum","nCombExpandUncertValue"],"nCombExpandUncertValue":3.9e-08},"nPropDigits":4,"nPropNumber":1,"tml_elements":["nPropNumber","nPropValue","nPropDigits","CombinedUncertainty"]}],"VariableValue":[{"nVarValue":333.15,"tml_elements":["nVarNumber","nVarValue","nVarDigits"],"nVarDigits":5,"nVarNumber":1}]}],"sCompiler":"GPC","dateDateAdded":"9/27/2010","nPureOrMixtureDataNumber":6,"eExpPurpose":"Principal objective of the work","Property":[{"PropPhaseID":{"tml_elements":["ePropPhase"],"ePropPhase":"Liquid"},"nPropNumber":1,"ePresentation":"Direct value, X","tml_elements":["nPropNumber","Property-MethodID","PropPhaseID","ePresentation","CombinedUncertainty"],"Property-MethodID":{"PropertyGroup":{"CompositionAtPhaseEquilibrium":{"ePropName":"Mole fraction","sMethodName":"Static equilibrium method","tml_elements":["ePropName","sMethodName"]},"tml_elements":["CompositionAtPhaseEquilibrium"]},"tml_elements":["PropertyGroup","RegNum"],"RegNum":{"nOrgNum":6,"tml_elements":["nOrgNum"]}},"CombinedUncertainty":{"nCombUncertLevOfConfid":95,"eCombUncertEvalMethod":"Propagation of evaluated standard uncertainties","tml_elements":["nCombUncertAssessNum","sCombUncertEvaluator","eCombUncertEvalMethod","nCombUncertLevOfConfid"],"sCombUncertEvaluator":"Data file compiler","nCombUncertAssessNum":1}}],"Variable":[{"tml_elements":["nVarNumber","VariableID","VarPhaseID"],"nVarNumber":1,"VarPhaseID":{"eVarPhase":"Liquid","tml_elements":["eVarPhase"]},"VariableID":{"VariableType":{"eTemperature":"Temperature, K","tml_elements":["eTemperature"]},"tml_elements":["VariableType"]}}],"sContributor":"TRC","Constraint":[{"nConstraintValue":101,"tml_elements":["nConstraintNumber","ConstraintID","ConstraintPhaseID","nConstraintValue","nConstrDigits"],"ConstraintID":{"tml_elements":["ConstraintType"],"ConstraintType":{"tml_elements":["ePressure"],"ePressure":"Pressure, kPa"}},"nConstraintNumber":1,"nConstrDigits":3,"ConstraintPhaseID":{"tml_elements":["eConstraintPhase"],"eConstraintPhase":"Liquid"}}],"Component":[{"RegNum":{"nOrgNum":7,"tml_elements":["nOrgNum"]},"nSampleNm":1,"tml_elements":["RegNum","nSampleNm"]},{"tml_elements":["RegNum","nSampleNm"],"nSampleNm":1,"RegNum":{"tml_elements":["nOrgNum"],"nOrgNum":6}}],"PhaseID":[{"tml_elements":["ePhase"],"ePhase":"Liquid"},{"RegNum":{"tml_elements":["nOrgNum"],"nOrgNum":6},"tml_elements":["ePhase","RegNum"],"ePhase":"Crystal"}],"tml_elements":["nPureOrMixtureDataNumber","Component","eExpPurpose","sCompiler","sContributor","dateDateAdded","Property","PhaseID","Constraint","Variable","NumValues"]}],"THERMOML_MD5_CHECKSUM":"89706af96e3a4afb2a4e4d1d2cf8fc9e","Compound":[{"sFormulaMolec":"C18H20FN3O4","Sample":[{"purity":[{"nStep":1,"tml_elements":["nStep","ePurifMethod"],"ePurifMethod":["Crystallization from solution"]},{"nPurityMass":99.6,"sAnalMeth":["(UV-spectrometry)"],"nPurityMassDigits":3,"tml_elements":["nStep","nPurityMass","nPurityMassDigits","sAnalMeth"],"nStep":2}],"tml_elements":["nSampleNm","eSource","purity"],"nSampleNm":1,"eSource":"Commercial source"}],"sCommonName":["ofloxacin"],"tml_elements":["RegNum","sStandardInChI","sStandardInChIKey","sCommonName","sFormulaMolec","Sample"],"sStandardInChIKey":"GSDSWSVVBLHKDQ-UHFFFAOYSA-N","sStandardInChI":"InChI=1S/C18H20FN3O4/c1-10-9-26-17-14-11(16(23)12(18(24)25)8-22(10)14)7-13(19)15(17)21-5-3-20(2)4-6-21/h7-8,10H,3-6,9H2,1-2H3,(H,24,25)","RegNum":{"tml_elements":["nOrgNum"],"nOrgNum":1}},{"sStandardInChI":"InChI=1S/C16H18FN3O3/c1-2-19-9-11(16(22)23)15(21)10-7-12(17)14(8-13(10)19)20-5-3-18-4-6-20/h7-9,18H,2-6H2,1H3,(H,22,23)","RegNum":{"tml_elements":["nOrgNum"],"nOrgNum":2},"sStandardInChIKey":"OGJPXUAPXNRGGI-UHFFFAOYSA-N","tml_elements":["RegNum","sStandardInChI","sStandardInChIKey","sCommonName","sFormulaMolec","Sample"],"sCommonName":["norfloxacin"],"Sample":[{"nSampleNm":1,"eSource":"Commercial source","tml_elements":["nSampleNm","eSource","purity"],"purity":[{"ePurifMethod":["Crystallization from solution"],"tml_elements":["nStep","ePurifMethod"],"nStep":1},{"nPurityMassDigits":3,"tml_elements":["nStep","nPurityMass","nPurityMassDigits","sAnalMeth"],"nStep":2,"sAnalMeth":["(UV-spectrometry)"],"nPurityMass":99.6}]}],"sFormulaMolec":"C16H18FN3O3"},{"sStandardInChIKey":"ZEKZLJVOYLTDKK-UHFFFAOYSA-N","sStandardInChI":"InChI=1S/C17H19F2N3O3/c1-3-21-8-11(17(24)25)16(23)10-6-12(18)15(13(19)14(10)21)22-5-4-20-9(2)7-22/h6,8-9,20H,3-5,7H2,1-2H3,(H,24,25)","RegNum":{"tml_elements":["nOrgNum"],"nOrgNum":3},"tml_elements":["RegNum","sStandardInChI","sStandardInChIKey","sCommonName","sFormulaMolec","Sample"],"sCommonName":["lomefloxacin"],"Sample":[{"nSampleNm":1,"eSource":"Commercial source","purity":[{"nStep":1,"tml_elements":["nStep","ePurifMethod"],"ePurifMethod":["Crystallization from solution"]},{"nPurityMassDigits":3,"tml_elements":["nStep","nPurityMass","nPurityMassDigits","sAnalMeth"],"nStep":2,"sAnalMeth":["(UV-spectrometry)"],"nPurityMass":99.6}],"tml_elements":["nSampleNm","eSource","purity"]}],"sFormulaMolec":"C17H19F2N3O3"},{"sStandardInChIKey":"MYSWGUAQZAJSOK-UHFFFAOYSA-N","sStandardInChI":"InChI=1S/C17H18FN3O3/c18-13-7-11-14(8-15(13)20-5-3-19-4-6-20)21(10-1-2-10)9-12(16(11)22)17(23)24/h7-10,19H,1-6H2,(H,23,24)","RegNum":{"tml_elements":["nOrgNum"],"nOrgNum":4},"sFormulaMolec":"C17H18FN3O3","tml_elements":["RegNum","sStandardInChI","sStandardInChIKey","sCommonName","sFormulaMolec","Sample"],"sCommonName":["ciprofloxacin"],"Sample":[{"tml_elements":["nSampleNm","eSource","purity"],"purity":[{"tml_elements":["nStep","ePurifMethod"],"nStep":1,"ePurifMethod":["Crystallization from solution"]},{"sAnalMeth":["(UV-spectrometry)"],"nPurityMass":99.6,"nStep":2,"tml_elements":["nStep","nPurityMass","nPurityMassDigits","sAnalMeth"],"nPurityMassDigits":3}],"eSource":"Commercial source","nSampleNm":1}]},{"Sample":[{"purity":[{"ePurifMethod":["Crystallization from solution"],"nStep":1,"tml_elements":["nStep","ePurifMethod"]},{"sAnalMeth":["(UV-spectrometry)"],"nPurityMass":99.6,"nStep":2,"tml_elements":["nStep","nPurityMass","nPurityMassDigits","sAnalMeth"],"nPurityMassDigits":3}],"tml_elements":["nSampleNm","eSource","purity"],"eSource":"Commercial source","nSampleNm":1}],"tml_elements":["RegNum","sStandardInChI","sStandardInChIKey","sCommonName","sFormulaMolec","Sample"],"sCommonName":["pefloxacin"],"sFormulaMolec":"C17H20FN3O3","sStandardInChIKey":"FHFYDNQZQSQIAI-UHFFFAOYSA-N","RegNum":{"tml_elements":["nOrgNum"],"nOrgNum":5},"sStandardInChI":"InChI=1S/C17H20FN3O3/c1-3-20-10-12(17(23)24)16(22)11-8-13(18)15(9-14(11)20)21-6-4-19(2)5-7-21/h8-10H,3-7H2,1-2H3,(H,23,24)"},{"sFormulaMolec":"C14H17N5O3","Sample":[{"nSampleNm":1,"eSource":"Commercial source","tml_elements":["nSampleNm","eSource","purity"],"purity":[{"ePurifMethod":["Crystallization from solution"],"nStep":1,"tml_elements":["nStep","ePurifMethod"]},{"nPurityMass":99.6,"sAnalMeth":["(UV-spectrometry)"],"nStep":2,"nPurityMassDigits":3,"tml_elements":["nStep","nPurityMass","nPurityMassDigits","sAnalMeth"]}]}],"tml_elements":["RegNum","sStandardInChI","sStandardInChIKey","sCommonName","sFormulaMolec","Sample"],"sCommonName":["8-ethyl-5,8-dihydro-5-oxo-2-(1-piperazinyl)pyrido[2,3-d]pyrimidine-6-carboxylic acid","pipemidic acid","pyrido[2,3-d]pyrimidine-6-carboxylic acid, 8-ethyl-5,8-dihydro-5-oxo-2-(1-piperazinyl)-"],"RegNum":{"tml_elements":["nOrgNum"],"nOrgNum":6},"sStandardInChI":"InChI=1S/C14H17N5O3/c1-2-18-8-10(13(21)22)11(20)9-7-16-14(17-12(9)18)19-5-3-15-4-6-19/h7-8,15H,2-6H2,1H3,(H,21,22)","sStandardInChIKey":"JOHZPMXAZQZXHR-UHFFFAOYSA-N"},{"sFormulaMolec":"C8H18O","Sample":[{"nSampleNm":1,"eSource":"Commercial source","purity":[],"tml_elements":["nSampleNm","eSource","purity"]}],"sCommonName":["octan-1-ol","1-octanol","capryl alcohol","caprylic alcohol","n-octyl alcohol","octanol","octyl alcohol"],"tml_elements":["RegNum","sStandardInChI","sStandardInChIKey","sCommonName","sFormulaMolec","Sample"],"sStandardInChIKey":"KBPLFHHGFOOTCA-UHFFFAOYSA-N","sStandardInChI":"InChI=1S/C8H18O/c1-2-3-4-5-6-7-8-9/h9H,2-8H2,1H3","RegNum":{"nOrgNum":7,"tml_elements":["nOrgNum"]}}],"Citation":{"sPubName":"J. Chem. Eng. Data","yrPubYr":"2010","sIDNum":"9","dateCit":"2020-09-29","sPage":"4033-4035","eType":"journal","sVol":"55","eSourceType":"Original","sDOI":"10.1021/je100116u","sTitle":"Determination and Correlation for Solubilities of Ofloxacin, Norfloxacin, Lomefloxacin, Ciprofloxacin, Pefloxacin, and Pipemidic Acid in 1-Octanol from (293.15 to 333.15) K","TRCRefID":{"yrYrPub":"2010","nAuthorn":"0","tml_elements":["yrYrPub","sAuthor1","sAuthor2","nAuthorn"],"sAuthor2":"wan","sAuthor1":"zha"},"sAbstract":"The solubilities of ofloxacin, norfloxacin, lomefloxacin, ciprofloxacin, pefloxacin, and pipemidic acid in 1-octanol have been determined from (293.15 to 333.15) K by a static equilibrium method. The experimental data were correlated with the modified Apelblat equation.","sAuthor":["Zhang, C.-L.[Cong-Liang]","Wang, Y.[Yan]"],"tml_elements":["TRCRefID","eType","eSourceType","sAuthor","sPubName","yrPubYr","dateCit","sTitle","sAbstract","sDOI","sIDNum","sVol","sPage"]}}