{"Version":{"tml_elements":["nVersionMajor","nVersionMinor"],"nVersionMajor":2,"nVersionMinor":0},"Citation":{"eSourceType":"Original","sKeyword":["Calorimetry","Liquid alloys","Lead free solders","Ni-Sb-Sn"],"sAuthor":["Elmahfoudi, A.[Aicha]","Furtauer, S.","Sabbae, A.[Abdelaziz]","Flandorfer, H.[Hans]"],"tml_elements":["TRCRefID","eType","eSourceType","sAuthor","sPubName","yrPubYr","dateCit","sTitle","sAbstract","sKeyword","sDOI","sVol","sPage"],"sDOI":"10.1016/j.tca.2012.01.024","sTitle":"Enthalpy of mixing of liquid systems for lead free soldering: The Ni-Sb-Sn system","TRCRefID":{"yrYrPub":"2012","tml_elements":["yrYrPub","sAuthor1","sAuthor2","nAuthorn"],"nAuthorn":"0","sAuthor2":"fur","sAuthor1":"elm"},"sAbstract":"The partial and integral enthalpies of mixing of liquid ternary Ni-Sb-Sn alloys were  determined along five sections, xSb /xSn =3:1, xSb /xSn =1:1, xSb /xSn =1:3, xNi /xSn =1:4, and xNi  /xSb =1:4 at 1000centsXC in a large compositional range using drop calorimetry techniques. The  binary data were carefully evaluated from literature values. Our measured ternary data were  fitted on the basis of an extended Redlich-Kister-Muggianu model for substitutional solutions  and an isoenthalpy plot could be established. The entire ternary system shows exothermic  values of  'mixH ranging from approx. -1000 J/mol in the Sb-Sn binary system to almost -  20000 J/mol towards Ni-Sb and Ni-Sn. No significant ternary interaction could be observed","dateCit":"2020-09-29","yrPubYr":"2012","sPubName":"Thermochim. Acta","eType":"journal","sVol":"534","sPage":"33-40"},"PureOrMixtureData":[{"Variable":[{"VarPhaseID":{"tml_elements":["eVarPhase"],"eVarPhase":"Liquid"},"nVarNumber":1,"tml_elements":["nVarNumber","VariableID","VarPhaseID"],"VariableID":{"VariableType":{"tml_elements":["eComponentComposition"],"eComponentComposition":"Mole fraction"},"tml_elements":["VariableType","RegNum"],"RegNum":{"tml_elements":["nOrgNum"],"nOrgNum":3}}}],"sContributor":"TRC","Constraint":[{"ConstraintPhaseID":{"tml_elements":["eConstraintPhase"],"eConstraintPhase":"Liquid"},"tml_elements":["nConstraintNumber","ConstraintID","ConstraintPhaseID","nConstraintValue","nConstrDigits"],"ConstraintID":{"ConstraintType":{"tml_elements":["ePressure"],"ePressure":"Pressure, kPa"},"tml_elements":["ConstraintType"]},"nConstrDigits":3,"nConstraintNumber":1,"nConstraintValue":101},{"nConstrDigits":5,"nConstraintNumber":2,"ConstraintID":{"tml_elements":["ConstraintType"],"ConstraintType":{"eTemperature":"Temperature, K","tml_elements":["eTemperature"]}},"ConstraintPhaseID":{"tml_elements":["eConstraintPhase"],"eConstraintPhase":"Liquid"},"nConstraintValue":1273.2,"tml_elements":["nConstraintNumber","ConstraintID","ConstraintPhaseID","nConstraintValue","nConstrDigits"]}],"Component":[{"nSampleNm":1,"RegNum":{"nOrgNum":2,"tml_elements":["nOrgNum"]},"tml_elements":["RegNum","nSampleNm"]},{"RegNum":{"tml_elements":["nOrgNum"],"nOrgNum":3},"nSampleNm":1,"tml_elements":["RegNum","nSampleNm"]}],"PhaseID":[{"ePhase":"Liquid","tml_elements":["ePhase"]}],"tml_elements":["nPureOrMixtureDataNumber","Component","eExpPurpose","sCompiler","sContributor","dateDateAdded","Property","PhaseID","Constraint","Variable","NumValues"],"NumValues":[{"VariableValue":[{"nVarNumber":1,"tml_elements":["nVarNumber","nVarValue","nVarDigits"],"nVarDigits":4,"nVarValue":0.2665}],"tml_elements":["VariableValue","PropertyValue"],"PropertyValue":[{"tml_elements":["nPropNumber","nPropValue","nPropDigits","CombinedUncertainty"],"nPropDigits":4,"nPropNumber":1,"CombinedUncertainty":{"nCombUncertAssessNum":1,"nCombExpandUncertValue":0.012,"tml_elements":["nCombUncertAssessNum","nCombExpandUncertValue"]},"nPropValue":-1.076}]},{"PropertyValue":[{"nPropValue":-1.32,"CombinedUncertainty":{"nCombUncertAssessNum":1,"tml_elements":["nCombUncertAssessNum","nCombExpandUncertValue"],"nCombExpandUncertValue":0.014},"nPropNumber":1,"nPropDigits":4,"tml_elements":["nPropNumber","nPropValue","nPropDigits","CombinedUncertainty"]}],"tml_elements":["VariableValue","PropertyValue"],"VariableValue":[{"nVarNumber":1,"nVarDigits":4,"tml_elements":["nVarNumber","nVarValue","nVarDigits"],"nVarValue":0.4886}]},{"PropertyValue":[{"nPropValue":-0.974,"CombinedUncertainty":{"nCombUncertAssessNum":1,"tml_elements":["nCombUncertAssessNum","nCombExpandUncertValue"],"nCombExpandUncertValue":0.011},"tml_elements":["nPropNumber","nPropValue","nPropDigits","CombinedUncertainty"],"nPropDigits":3,"nPropNumber":1}],"tml_elements":["VariableValue","PropertyValue"],"VariableValue":[{"nVarValue":0.7372,"nVarDigits":4,"tml_elements":["nVarNumber","nVarValue","nVarDigits"],"nVarNumber":1}]}],"sCompiler":"VVD","nPureOrMixtureDataNumber":1,"dateDateAdded":"4/3/2012","eExpPurpose":"Principal objective of the work","Property":[{"Property-MethodID":{"PropertyGroup":{"tml_elements":["ExcessPartialApparentEnergyProp"],"ExcessPartialApparentEnergyProp":{"eMethodName":"Calvet calorimetry","ePropName":"Excess molar enthalpy (molar enthalpy of mixing), kJ/mol","tml_elements":["ePropName","eMethodName"]}},"tml_elements":["PropertyGroup"]},"CombinedUncertainty":{"sCombUncertEvaluator":"Data file compiler","nCombUncertAssessNum":1,"nCombUncertLevOfConfid":95,"eCombUncertEvalMethod":"Propagation of evaluated standard uncertainties","tml_elements":["nCombUncertAssessNum","sCombUncertEvaluator","eCombUncertEvalMethod","nCombUncertLevOfConfid"]},"nPropNumber":1,"PropPhaseID":{"tml_elements":["ePropPhase"],"ePropPhase":"Liquid"},"tml_elements":["nPropNumber","Property-MethodID","PropPhaseID","ePresentation","CombinedUncertainty"],"ePresentation":"Direct value, X"}]},{"tml_elements":["nPureOrMixtureDataNumber","Component","eExpPurpose","sCompiler","sContributor","dateDateAdded","Property","PhaseID","Variable","NumValues"],"PhaseID":[{"ePhase":"Liquid","tml_elements":["ePhase"]}],"sContributor":"TRC","Property":[{"CombinedUncertainty":{"tml_elements":["nCombUncertAssessNum","sCombUncertEvaluator","eCombUncertEvalMethod","nCombUncertLevOfConfid"],"eCombUncertEvalMethod":"Propagation of evaluated standard uncertainties","nCombUncertLevOfConfid":95,"nCombUncertAssessNum":1,"sCombUncertEvaluator":"Data file compiler"},"PropPhaseID":{"tml_elements":["ePropPhase"],"ePropPhase":"Liquid"},"Property-MethodID":{"PropertyGroup":{"tml_elements":["ExcessPartialApparentEnergyProp"],"ExcessPartialApparentEnergyProp":{"tml_elements":["ePropName","eMethodName"],"eMethodName":"Calvet calorimetry","ePropName":"Excess molar enthalpy (molar enthalpy of mixing), kJ/mol"}},"tml_elements":["PropertyGroup"]},"nPropNumber":1,"ePresentation":"Direct value, X","tml_elements":["nPropNumber","Property-MethodID","PropPhaseID","ePresentation","CombinedUncertainty"]}],"eExpPurpose":"Principal objective of the work","nPureOrMixtureDataNumber":2,"dateDateAdded":"4/3/2012","sCompiler":"VVD","NumValues":[{"tml_elements":["VariableValue","PropertyValue"],"PropertyValue":[{"nPropValue":-9.592,"CombinedUncertainty":{"nCombExpandUncertValue":0.097,"tml_elements":["nCombUncertAssessNum","nCombExpandUncertValue"],"nCombUncertAssessNum":1},"tml_elements":["nPropNumber","nPropValue","nPropDigits","CombinedUncertainty"],"nPropNumber":1,"nPropDigits":4}],"VariableValue":[{"nVarValue":0.213,"tml_elements":["nVarNumber","nVarValue","nVarDigits"],"nVarDigits":4,"nVarNumber":1},{"nVarNumber":2,"nVarDigits":3,"tml_elements":["nVarNumber","nVarValue","nVarDigits"],"nVarValue":101},{"tml_elements":["nVarNumber","nVarValue","nVarDigits"],"nVarDigits":5,"nVarNumber":3,"nVarValue":1273.2}]}],"Component":[{"RegNum":{"tml_elements":["nOrgNum"],"nOrgNum":1},"nSampleNm":1,"tml_elements":["RegNum","nSampleNm"]},{"tml_elements":["RegNum","nSampleNm"],"nSampleNm":1,"RegNum":{"nOrgNum":2,"tml_elements":["nOrgNum"]}}],"Variable":[{"VariableID":{"VariableType":{"tml_elements":["eComponentComposition"],"eComponentComposition":"Mole fraction"},"tml_elements":["VariableType","RegNum"],"RegNum":{"tml_elements":["nOrgNum"],"nOrgNum":1}},"tml_elements":["nVarNumber","VariableID","VarPhaseID"],"VarPhaseID":{"eVarPhase":"Liquid","tml_elements":["eVarPhase"]},"nVarNumber":1},{"VariableID":{"VariableType":{"ePressure":"Pressure, kPa","tml_elements":["ePressure"]},"tml_elements":["VariableType"]},"tml_elements":["nVarNumber","VariableID","VarPhaseID"],"nVarNumber":2,"VarPhaseID":{"tml_elements":["eVarPhase"],"eVarPhase":"Liquid"}},{"tml_elements":["nVarNumber","VariableID","VarPhaseID"],"VarPhaseID":{"tml_elements":["eVarPhase"],"eVarPhase":"Liquid"},"nVarNumber":3,"VariableID":{"tml_elements":["VariableType"],"VariableType":{"tml_elements":["eTemperature"],"eTemperature":"Temperature, K"}}}]},{"nPureOrMixtureDataNumber":3,"dateDateAdded":"4/3/2012","sCompiler":"VVD","NumValues":[{"VariableValue":[{"nVarValue":0.2109,"nVarNumber":1,"nVarDigits":4,"tml_elements":["nVarNumber","nVarValue","nVarDigits"]},{"tml_elements":["nVarNumber","nVarValue","nVarDigits"],"nVarDigits":3,"nVarNumber":2,"nVarValue":101},{"nVarNumber":3,"nVarDigits":5,"tml_elements":["nVarNumber","nVarValue","nVarDigits"],"nVarValue":1273.2}],"PropertyValue":[{"tml_elements":["nPropNumber","nPropValue","nPropDigits","CombinedUncertainty"],"nPropNumber":1,"nPropDigits":5,"CombinedUncertainty":{"nCombUncertAssessNum":1,"nCombExpandUncertValue":0.109,"tml_elements":["nCombUncertAssessNum","nCombExpandUncertValue"]},"nPropValue":-10.782}],"tml_elements":["VariableValue","PropertyValue"]}],"Property":[{"CombinedUncertainty":{"tml_elements":["nCombUncertAssessNum","sCombUncertEvaluator","eCombUncertEvalMethod","nCombUncertLevOfConfid"],"nCombUncertLevOfConfid":95,"eCombUncertEvalMethod":"Propagation of evaluated standard uncertainties","nCombUncertAssessNum":1,"sCombUncertEvaluator":"Data file compiler"},"tml_elements":["nPropNumber","Property-MethodID","PropPhaseID","ePresentation","CombinedUncertainty"],"ePresentation":"Direct value, X","nPropNumber":1,"PropPhaseID":{"ePropPhase":"Liquid","tml_elements":["ePropPhase"]},"Property-MethodID":{"tml_elements":["PropertyGroup"],"PropertyGroup":{"ExcessPartialApparentEnergyProp":{"eMethodName":"Calvet calorimetry","ePropName":"Excess molar enthalpy (molar enthalpy of mixing), kJ/mol","tml_elements":["ePropName","eMethodName"]},"tml_elements":["ExcessPartialApparentEnergyProp"]}}}],"eExpPurpose":"Principal objective of the work","sContributor":"TRC","Variable":[{"VariableID":{"VariableType":{"tml_elements":["eComponentComposition"],"eComponentComposition":"Mole fraction"},"tml_elements":["VariableType","RegNum"],"RegNum":{"tml_elements":["nOrgNum"],"nOrgNum":1}},"VarPhaseID":{"tml_elements":["eVarPhase"],"eVarPhase":"Liquid"},"nVarNumber":1,"tml_elements":["nVarNumber","VariableID","VarPhaseID"]},{"VariableID":{"VariableType":{"tml_elements":["ePressure"],"ePressure":"Pressure, kPa"},"tml_elements":["VariableType"]},"tml_elements":["nVarNumber","VariableID","VarPhaseID"],"VarPhaseID":{"eVarPhase":"Liquid","tml_elements":["eVarPhase"]},"nVarNumber":2},{"VariableID":{"VariableType":{"eTemperature":"Temperature, K","tml_elements":["eTemperature"]},"tml_elements":["VariableType"]},"tml_elements":["nVarNumber","VariableID","VarPhaseID"],"nVarNumber":3,"VarPhaseID":{"eVarPhase":"Liquid","tml_elements":["eVarPhase"]}}],"tml_elements":["nPureOrMixtureDataNumber","Component","eExpPurpose","sCompiler","sContributor","dateDateAdded","Property","PhaseID","Variable","NumValues"],"PhaseID":[{"tml_elements":["ePhase"],"ePhase":"Liquid"}],"Component":[{"tml_elements":["RegNum","nSampleNm"],"RegNum":{"nOrgNum":1,"tml_elements":["nOrgNum"]},"nSampleNm":1},{"tml_elements":["RegNum","nSampleNm"],"nSampleNm":1,"RegNum":{"nOrgNum":3,"tml_elements":["nOrgNum"]}}]},{"eExpPurpose":"Principal objective of the work","Property":[{"CombinedUncertainty":{"tml_elements":["nCombUncertAssessNum","sCombUncertEvaluator","eCombUncertEvalMethod","nCombUncertLevOfConfid"],"eCombUncertEvalMethod":"Propagation of evaluated standard uncertainties","nCombUncertLevOfConfid":95,"nCombUncertAssessNum":1,"sCombUncertEvaluator":"Data file compiler"},"ePresentation":"Direct value, X","tml_elements":["nPropNumber","Property-MethodID","PropPhaseID","ePresentation","CombinedUncertainty"],"Property-MethodID":{"PropertyGroup":{"tml_elements":["ExcessPartialApparentEnergyProp"],"ExcessPartialApparentEnergyProp":{"tml_elements":["ePropName","eMethodName"],"eMethodName":"Calvet calorimetry","ePropName":"Excess molar enthalpy (molar enthalpy of mixing), kJ/mol"}},"tml_elements":["PropertyGroup"]},"PropPhaseID":{"tml_elements":["ePropPhase"],"ePropPhase":"Liquid"},"nPropNumber":1}],"NumValues":[{"tml_elements":["VariableValue","PropertyValue"],"PropertyValue":[{"nPropValue":-1.076,"CombinedUncertainty":{"tml_elements":["nCombUncertAssessNum","nCombExpandUncertValue"],"nCombExpandUncertValue":0.012,"nCombUncertAssessNum":1},"tml_elements":["nPropNumber","nPropValue","nPropDigits","CombinedUncertainty"],"nPropNumber":1,"nPropDigits":4}],"VariableValue":[{"nVarValue":0,"tml_elements":["nVarNumber","nVarValue","nVarDigits"],"nVarDigits":2,"nVarNumber":1},{"nVarValue":0.2665,"nVarDigits":4,"tml_elements":["nVarNumber","nVarValue","nVarDigits"],"nVarNumber":2}]},{"VariableValue":[{"nVarValue":0,"nVarNumber":1,"nVarDigits":2,"tml_elements":["nVarNumber","nVarValue","nVarDigits"]},{"nVarValue":0.4886,"nVarDigits":4,"tml_elements":["nVarNumber","nVarValue","nVarDigits"],"nVarNumber":2}],"PropertyValue":[{"nPropValue":-1.32,"CombinedUncertainty":{"tml_elements":["nCombUncertAssessNum","nCombExpandUncertValue"],"nCombExpandUncertValue":0.014,"nCombUncertAssessNum":1},"tml_elements":["nPropNumber","nPropValue","nPropDigits","CombinedUncertainty"],"nPropDigits":4,"nPropNumber":1}],"tml_elements":["VariableValue","PropertyValue"]},{"PropertyValue":[{"nPropDigits":3,"nPropNumber":1,"tml_elements":["nPropNumber","nPropValue","nPropDigits","CombinedUncertainty"],"CombinedUncertainty":{"nCombExpandUncertValue":0.011,"tml_elements":["nCombUncertAssessNum","nCombExpandUncertValue"],"nCombUncertAssessNum":1},"nPropValue":-0.974}],"tml_elements":["VariableValue","PropertyValue"],"VariableValue":[{"tml_elements":["nVarNumber","nVarValue","nVarDigits"],"nVarDigits":2,"nVarNumber":1,"nVarValue":0},{"nVarNumber":2,"tml_elements":["nVarNumber","nVarValue","nVarDigits"],"nVarDigits":4,"nVarValue":0.7372}]},{"VariableValue":[{"nVarDigits":3,"tml_elements":["nVarNumber","nVarValue","nVarDigits"],"nVarNumber":1,"nVarValue":0.0278},{"nVarValue":0.2591,"nVarDigits":4,"tml_elements":["nVarNumber","nVarValue","nVarDigits"],"nVarNumber":2}],"tml_elements":["VariableValue","PropertyValue"],"PropertyValue":[{"nPropValue":-2.402,"CombinedUncertainty":{"nCombExpandUncertValue":0.025,"tml_elements":["nCombUncertAssessNum","nCombExpandUncertValue"],"nCombUncertAssessNum":1},"tml_elements":["nPropNumber","nPropValue","nPropDigits","CombinedUncertainty"],"nPropNumber":1,"nPropDigits":4}]},{"tml_elements":["VariableValue","PropertyValue"],"PropertyValue":[{"CombinedUncertainty":{"tml_elements":["nCombUncertAssessNum","nCombExpandUncertValue"],"nCombExpandUncertValue":0.026,"nCombUncertAssessNum":1},"nPropValue":-2.547,"tml_elements":["nPropNumber","nPropValue","nPropDigits","CombinedUncertainty"],"nPropNumber":1,"nPropDigits":4}],"VariableValue":[{"nVarNumber":1,"tml_elements":["nVarNumber","nVarValue","nVarDigits"],"nVarDigits":3,"nVarValue":0.0306},{"nVarDigits":4,"tml_elements":["nVarNumber","nVarValue","nVarDigits"],"nVarNumber":2,"nVarValue":0.7146}]},{"VariableValue":[{"nVarValue":0.0476,"nVarNumber":1,"tml_elements":["nVarNumber","nVarValue","nVarDigits"],"nVarDigits":3},{"nVarDigits":4,"tml_elements":["nVarNumber","nVarValue","nVarDigits"],"nVarNumber":2,"nVarValue":0.4654}],"PropertyValue":[{"CombinedUncertainty":{"nCombExpandUncertValue":0.037,"tml_elements":["nCombUncertAssessNum","nCombExpandUncertValue"],"nCombUncertAssessNum":1},"nPropValue":-3.624,"tml_elements":["nPropNumber","nPropValue","nPropDigits","CombinedUncertainty"],"nPropNumber":1,"nPropDigits":4}],"tml_elements":["VariableValue","PropertyValue"]},{"tml_elements":["VariableValue","PropertyValue"],"PropertyValue":[{"CombinedUncertainty":{"nCombUncertAssessNum":1,"nCombExpandUncertValue":0.038,"tml_elements":["nCombUncertAssessNum","nCombExpandUncertValue"]},"nPropValue":-3.693,"tml_elements":["nPropNumber","nPropValue","nPropDigits","CombinedUncertainty"],"nPropNumber":1,"nPropDigits":4}],"VariableValue":[{"nVarValue":0.0546,"nVarNumber":1,"nVarDigits":3,"tml_elements":["nVarNumber","nVarValue","nVarDigits"]},{"nVarValue":0.252,"nVarNumber":2,"nVarDigits":4,"tml_elements":["nVarNumber","nVarValue","nVarDigits"]}]},{"PropertyValue":[{"nPropDigits":4,"nPropNumber":1,"tml_elements":["nPropNumber","nPropValue","nPropDigits","CombinedUncertainty"],"CombinedUncertainty":{"nCombUncertAssessNum":1,"tml_elements":["nCombUncertAssessNum","nCombExpandUncertValue"],"nCombExpandUncertValue":0.043},"nPropValue":-4.178}],"tml_elements":["VariableValue","PropertyValue"],"VariableValue":[{"nVarValue":0.0625,"nVarNumber":1,"nVarDigits":3,"tml_elements":["nVarNumber","nVarValue","nVarDigits"]},{"nVarValue":0.6911,"tml_elements":["nVarNumber","nVarValue","nVarDigits"],"nVarDigits":4,"nVarNumber":2}]},{"tml_elements":["VariableValue","PropertyValue"],"PropertyValue":[{"nPropValue":-5.902,"CombinedUncertainty":{"nCombUncertAssessNum":1,"nCombExpandUncertValue":0.06,"tml_elements":["nCombUncertAssessNum","nCombExpandUncertValue"]},"tml_elements":["nPropNumber","nPropValue","nPropDigits","CombinedUncertainty"],"nPropNumber":1,"nPropDigits":4}],"VariableValue":[{"nVarDigits":3,"tml_elements":["nVarNumber","nVarValue","nVarDigits"],"nVarNumber":1,"nVarValue":0.0818},{"nVarValue":0.6157,"tml_elements":["nVarNumber","nVarValue","nVarDigits"],"nVarDigits":4,"nVarNumber":2}]},{"tml_elements":["VariableValue","PropertyValue"],"PropertyValue":[{"CombinedUncertainty":{"nCombUncertAssessNum":1,"tml_elements":["nCombUncertAssessNum","nCombExpandUncertValue"],"nCombExpandUncertValue":0.051},"nPropValue":-5.044,"nPropDigits":4,"nPropNumber":1,"tml_elements":["nPropNumber","nPropValue","nPropDigits","CombinedUncertainty"]}],"VariableValue":[{"nVarNumber":1,"nVarDigits":3,"tml_elements":["nVarNumber","nVarValue","nVarDigits"],"nVarValue":0.0828},{"nVarNumber":2,"tml_elements":["nVarNumber","nVarValue","nVarDigits"],"nVarDigits":4,"nVarValue":0.2444}]},{"VariableValue":[{"nVarValue":0.0856,"nVarNumber":1,"tml_elements":["nVarNumber","nVarValue","nVarDigits"],"nVarDigits":3},{"nVarValue":0.5978,"nVarNumber":2,"tml_elements":["nVarNumber","nVarValue","nVarDigits"],"nVarDigits":4}],"PropertyValue":[{"tml_elements":["nPropNumber","nPropValue","nPropDigits","CombinedUncertainty"],"nPropNumber":1,"nPropDigits":4,"CombinedUncertainty":{"nCombUncertAssessNum":1,"tml_elements":["nCombUncertAssessNum","nCombExpandUncertValue"],"nCombExpandUncertValue":0.062},"nPropValue":-6.123}],"tml_elements":["VariableValue","PropertyValue"]},{"PropertyValue":[{"tml_elements":["nPropNumber","nPropValue","nPropDigits","CombinedUncertainty"],"nPropNumber":1,"nPropDigits":4,"nPropValue":-6.323,"CombinedUncertainty":{"tml_elements":["nCombUncertAssessNum","nCombExpandUncertValue"],"nCombExpandUncertValue":0.064,"nCombUncertAssessNum":1}}],"tml_elements":["VariableValue","PropertyValue"],"VariableValue":[{"tml_elements":["nVarNumber","nVarValue","nVarDigits"],"nVarDigits":3,"nVarNumber":1,"nVarValue":0.0898},{"nVarDigits":4,"tml_elements":["nVarNumber","nVarValue","nVarDigits"],"nVarNumber":2,"nVarValue":0.5785}]},{"tml_elements":["VariableValue","PropertyValue"],"PropertyValue":[{"tml_elements":["nPropNumber","nPropValue","nPropDigits","CombinedUncertainty"],"nPropDigits":4,"nPropNumber":1,"CombinedUncertainty":{"tml_elements":["nCombUncertAssessNum","nCombExpandUncertValue"],"nCombExpandUncertValue":0.066,"nCombUncertAssessNum":1},"nPropValue":-6.527}],"VariableValue":[{"nVarDigits":3,"tml_elements":["nVarNumber","nVarValue","nVarDigits"],"nVarNumber":1,"nVarValue":0.094},{"nVarValue":0.5586,"nVarNumber":2,"nVarDigits":4,"tml_elements":["nVarNumber","nVarValue","nVarDigits"]}]},{"tml_elements":["VariableValue","PropertyValue"],"PropertyValue":[{"CombinedUncertainty":{"nCombExpandUncertValue":0.059,"tml_elements":["nCombUncertAssessNum","nCombExpandUncertValue"],"nCombUncertAssessNum":1},"nPropValue":-5.825,"tml_elements":["nPropNumber","nPropValue","nPropDigits","CombinedUncertainty"],"nPropNumber":1,"nPropDigits":4}],"VariableValue":[{"nVarNumber":1,"tml_elements":["nVarNumber","nVarValue","nVarDigits"],"nVarDigits":3,"nVarValue":0.0947},{"tml_elements":["nVarNumber","nVarValue","nVarDigits"],"nVarDigits":4,"nVarNumber":2,"nVarValue":0.6674}]},{"tml_elements":["VariableValue","PropertyValue"],"PropertyValue":[{"tml_elements":["nPropNumber","nPropValue","nPropDigits","CombinedUncertainty"],"nPropDigits":4,"nPropNumber":1,"nPropValue":-5.991,"CombinedUncertainty":{"nCombUncertAssessNum":1,"tml_elements":["nCombUncertAssessNum","nCombExpandUncertValue"],"nCombExpandUncertValue":0.061}}],"VariableValue":[{"nVarNumber":1,"tml_elements":["nVarNumber","nVarValue","nVarDigits"],"nVarDigits":3,"nVarValue":0.096},{"nVarNumber":2,"tml_elements":["nVarNumber","nVarValue","nVarDigits"],"nVarDigits":4,"nVarValue":0.4417}]},{"tml_elements":["VariableValue","PropertyValue"],"PropertyValue":[{"tml_elements":["nPropNumber","nPropValue","nPropDigits","CombinedUncertainty"],"nPropDigits":4,"nPropNumber":1,"nPropValue":-6.735,"CombinedUncertainty":{"nCombUncertAssessNum":1,"nCombExpandUncertValue":0.068,"tml_elements":["nCombUncertAssessNum","nCombExpandUncertValue"]}}],"VariableValue":[{"nVarNumber":1,"nVarDigits":3,"tml_elements":["nVarNumber","nVarValue","nVarDigits"],"nVarValue":0.0983},{"nVarValue":0.5383,"nVarNumber":2,"tml_elements":["nVarNumber","nVarValue","nVarDigits"],"nVarDigits":4}]},{"PropertyValue":[{"nPropValue":-6.95,"CombinedUncertainty":{"nCombUncertAssessNum":1,"nCombExpandUncertValue":0.071,"tml_elements":["nCombUncertAssessNum","nCombExpandUncertValue"]},"tml_elements":["nPropNumber","nPropValue","nPropDigits","CombinedUncertainty"],"nPropNumber":1,"nPropDigits":4}],"tml_elements":["VariableValue","PropertyValue"],"VariableValue":[{"nVarValue":0.1024,"nVarNumber":1,"nVarDigits":4,"tml_elements":["nVarNumber","nVarValue","nVarDigits"]},{"nVarDigits":4,"tml_elements":["nVarNumber","nVarValue","nVarDigits"],"nVarNumber":2,"nVarValue":0.5193}]},{"VariableValue":[{"nVarNumber":1,"tml_elements":["nVarNumber","nVarValue","nVarDigits"],"nVarDigits":4,"nVarValue":0.1037},{"nVarValue":0.3879,"tml_elements":["nVarNumber","nVarValue","nVarDigits"],"nVarDigits":4,"nVarNumber":2}],"tml_elements":["VariableValue","PropertyValue"],"PropertyValue":[{"nPropValue":-6.806,"CombinedUncertainty":{"tml_elements":["nCombUncertAssessNum","nCombExpandUncertValue"],"nCombExpandUncertValue":0.069,"nCombUncertAssessNum":1},"nPropDigits":4,"nPropNumber":1,"tml_elements":["nPropNumber","nPropValue","nPropDigits","CombinedUncertainty"]}]},{"VariableValue":[{"nVarValue":0.1066,"nVarNumber":1,"tml_elements":["nVarNumber","nVarValue","nVarDigits"],"nVarDigits":4},{"nVarValue":0.4996,"nVarNumber":2,"nVarDigits":4,"tml_elements":["nVarNumber","nVarValue","nVarDigits"]}],"PropertyValue":[{"nPropValue":-7.106,"CombinedUncertainty":{"nCombExpandUncertValue":0.072,"tml_elements":["nCombUncertAssessNum","nCombExpandUncertValue"],"nCombUncertAssessNum":1},"tml_elements":["nPropNumber","nPropValue","nPropDigits","CombinedUncertainty"],"nPropDigits":4,"nPropNumber":1}],"tml_elements":["VariableValue","PropertyValue"]},{"VariableValue":[{"nVarValue":0.1073,"nVarNumber":1,"tml_elements":["nVarNumber","nVarValue","nVarDigits"],"nVarDigits":4},{"nVarNumber":2,"tml_elements":["nVarNumber","nVarValue","nVarDigits"],"nVarDigits":4,"nVarValue":0.4016}],"PropertyValue":[{"CombinedUncertainty":{"nCombUncertAssessNum":1,"tml_elements":["nCombUncertAssessNum","nCombExpandUncertValue"],"nCombExpandUncertValue":0.071},"nPropValue":-6.979,"tml_elements":["nPropNumber","nPropValue","nPropDigits","CombinedUncertainty"],"nPropNumber":1,"nPropDigits":4}],"tml_elements":["VariableValue","PropertyValue"]},{"tml_elements":["VariableValue","PropertyValue"],"PropertyValue":[{"CombinedUncertainty":{"tml_elements":["nCombUncertAssessNum","nCombExpandUncertValue"],"nCombExpandUncertValue":0.065,"nCombUncertAssessNum":1},"nPropValue":-6.389,"nPropNumber":1,"nPropDigits":4,"tml_elements":["nPropNumber","nPropValue","nPropDigits","CombinedUncertainty"]}],"VariableValue":[{"tml_elements":["nVarNumber","nVarValue","nVarDigits"],"nVarDigits":4,"nVarNumber":1,"nVarValue":0.111},{"nVarValue":0.2369,"tml_elements":["nVarNumber","nVarValue","nVarDigits"],"nVarDigits":4,"nVarNumber":2}]},{"PropertyValue":[{"tml_elements":["nPropNumber","nPropValue","nPropDigits","CombinedUncertainty"],"nPropNumber":1,"nPropDigits":4,"nPropValue":-7.276,"CombinedUncertainty":{"nCombUncertAssessNum":1,"nCombExpandUncertValue":0.074,"tml_elements":["nCombUncertAssessNum","nCombExpandUncertValue"]}}],"tml_elements":["VariableValue","PropertyValue"],"VariableValue":[{"nVarDigits":4,"tml_elements":["nVarNumber","nVarValue","nVarDigits"],"nVarNumber":1,"nVarValue":0.111},{"nVarNumber":2,"nVarDigits":4,"tml_elements":["nVarNumber","nVarValue","nVarDigits"],"nVarValue":0.479}]},{"PropertyValue":[{"CombinedUncertainty":{"nCombExpandUncertValue":0.073,"tml_elements":["nCombUncertAssessNum","nCombExpandUncertValue"],"nCombUncertAssessNum":1},"nPropValue":-7.207,"nPropNumber":1,"nPropDigits":4,"tml_elements":["nPropNumber","nPropValue","nPropDigits","CombinedUncertainty"]}],"tml_elements":["VariableValue","PropertyValue"],"VariableValue":[{"nVarValue":0.1111,"nVarNumber":1,"tml_elements":["nVarNumber","nVarValue","nVarDigits"],"nVarDigits":4},{"tml_elements":["nVarNumber","nVarValue","nVarDigits"],"nVarDigits":4,"nVarNumber":2,"nVarValue":0.4157}]},{"PropertyValue":[{"CombinedUncertainty":{"nCombExpandUncertValue":0.075,"tml_elements":["nCombUncertAssessNum","nCombExpandUncertValue"],"nCombUncertAssessNum":1},"nPropValue":-7.425,"nPropDigits":4,"nPropNumber":1,"tml_elements":["nPropNumber","nPropValue","nPropDigits","CombinedUncertainty"]}],"tml_elements":["VariableValue","PropertyValue"],"VariableValue":[{"nVarValue":0.115,"nVarNumber":1,"tml_elements":["nVarNumber","nVarValue","nVarDigits"],"nVarDigits":4},{"nVarNumber":2,"nVarDigits":4,"tml_elements":["nVarNumber","nVarValue","nVarDigits"],"nVarValue":0.4304}]},{"VariableValue":[{"nVarDigits":4,"tml_elements":["nVarNumber","nVarValue","nVarDigits"],"nVarNumber":1,"nVarValue":0.1154},{"nVarValue":0.4582,"nVarNumber":2,"tml_elements":["nVarNumber","nVarValue","nVarDigits"],"nVarDigits":4}],"PropertyValue":[{"nPropDigits":4,"nPropNumber":1,"tml_elements":["nPropNumber","nPropValue","nPropDigits","CombinedUncertainty"],"CombinedUncertainty":{"tml_elements":["nCombUncertAssessNum","nCombExpandUncertValue"],"nCombExpandUncertValue":0.075,"nCombUncertAssessNum":1},"nPropValue":-7.41}],"tml_elements":["VariableValue","PropertyValue"]},{"tml_elements":["VariableValue","PropertyValue"],"PropertyValue":[{"nPropValue":-7.576,"CombinedUncertainty":{"nCombExpandUncertValue":0.077,"tml_elements":["nCombUncertAssessNum","nCombExpandUncertValue"],"nCombUncertAssessNum":1},"tml_elements":["nPropNumber","nPropValue","nPropDigits","CombinedUncertainty"],"nPropNumber":1,"nPropDigits":4}],"VariableValue":[{"nVarDigits":4,"tml_elements":["nVarNumber","nVarValue","nVarDigits"],"nVarNumber":1,"nVarValue":0.1186},{"nVarDigits":4,"tml_elements":["nVarNumber","nVarValue","nVarDigits"],"nVarNumber":2,"nVarValue":0.4436}]},{"VariableValue":[{"nVarValue":0.1201,"nVarNumber":1,"tml_elements":["nVarNumber","nVarValue","nVarDigits"],"nVarDigits":4},{"nVarDigits":4,"tml_elements":["nVarNumber","nVarValue","nVarDigits"],"nVarNumber":2,"nVarValue":0.4359}],"tml_elements":["VariableValue","PropertyValue"],"PropertyValue":[{"nPropNumber":1,"nPropDigits":4,"tml_elements":["nPropNumber","nPropValue","nPropDigits","CombinedUncertainty"],"CombinedUncertainty":{"nCombUncertAssessNum":1,"tml_elements":["nCombUncertAssessNum","nCombExpandUncertValue"],"nCombExpandUncertValue":0.077},"nPropValue":-7.601}]},{"tml_elements":["VariableValue","PropertyValue"],"PropertyValue":[{"nPropValue":-7.734,"CombinedUncertainty":{"nCombUncertAssessNum":1,"tml_elements":["nCombUncertAssessNum","nCombExpandUncertValue"],"nCombExpandUncertValue":0.078},"tml_elements":["nPropNumber","nPropValue","nPropDigits","CombinedUncertainty"],"nPropNumber":1,"nPropDigits":4}],"VariableValue":[{"nVarNumber":1,"nVarDigits":4,"tml_elements":["nVarNumber","nVarValue","nVarDigits"],"nVarValue":0.1221},{"nVarNumber":2,"tml_elements":["nVarNumber","nVarValue","nVarDigits"],"nVarDigits":4,"nVarValue":0.4567}]},{"VariableValue":[{"tml_elements":["nVarNumber","nVarValue","nVarDigits"],"nVarDigits":4,"nVarNumber":1,"nVarValue":0.1253},{"nVarValue":0.4119,"nVarNumber":2,"nVarDigits":4,"tml_elements":["nVarNumber","nVarValue","nVarDigits"]}],"PropertyValue":[{"nPropValue":-7.801,"CombinedUncertainty":{"tml_elements":["nCombUncertAssessNum","nCombExpandUncertValue"],"nCombExpandUncertValue":0.079,"nCombUncertAssessNum":1},"tml_elements":["nPropNumber","nPropValue","nPropDigits","CombinedUncertainty"],"nPropDigits":4,"nPropNumber":1}],"tml_elements":["VariableValue","PropertyValue"]},{"VariableValue":[{"nVarValue":0.1257,"tml_elements":["nVarNumber","nVarValue","nVarDigits"],"nVarDigits":4,"nVarNumber":1},{"nVarValue":0.4702,"nVarNumber":2,"nVarDigits":4,"tml_elements":["nVarNumber","nVarValue","nVarDigits"]}],"PropertyValue":[{"nPropNumber":1,"nPropDigits":4,"tml_elements":["nPropNumber","nPropValue","nPropDigits","CombinedUncertainty"],"CombinedUncertainty":{"nCombUncertAssessNum":1,"tml_elements":["nCombUncertAssessNum","nCombExpandUncertValue"],"nCombExpandUncertValue":0.08},"nPropValue":-7.926}],"tml_elements":["VariableValue","PropertyValue"]},{"VariableValue":[{"tml_elements":["nVarNumber","nVarValue","nVarDigits"],"nVarDigits":4,"nVarNumber":1,"nVarValue":0.1275},{"tml_elements":["nVarNumber","nVarValue","nVarDigits"],"nVarDigits":4,"nVarNumber":2,"nVarValue":0.6432}],"PropertyValue":[{"tml_elements":["nPropNumber","nPropValue","nPropDigits","CombinedUncertainty"],"nPropNumber":1,"nPropDigits":4,"nPropValue":-7.502,"CombinedUncertainty":{"nCombExpandUncertValue":0.076,"tml_elements":["nCombUncertAssessNum","nCombExpandUncertValue"],"nCombUncertAssessNum":1}}],"tml_elements":["VariableValue","PropertyValue"]},{"VariableValue":[{"nVarValue":0.1294,"tml_elements":["nVarNumber","nVarValue","nVarDigits"],"nVarDigits":4,"nVarNumber":1},{"nVarDigits":4,"tml_elements":["nVarNumber","nVarValue","nVarDigits"],"nVarNumber":2,"nVarValue":0.4841}],"PropertyValue":[{"nPropValue":-8.057,"CombinedUncertainty":{"nCombUncertAssessNum":1,"nCombExpandUncertValue":0.082,"tml_elements":["nCombUncertAssessNum","nCombExpandUncertValue"]},"tml_elements":["nPropNumber","nPropValue","nPropDigits","CombinedUncertainty"],"nPropNumber":1,"nPropDigits":4}],"tml_elements":["VariableValue","PropertyValue"]},{"tml_elements":["VariableValue","PropertyValue"],"PropertyValue":[{"nPropDigits":4,"nPropNumber":1,"tml_elements":["nPropNumber","nPropValue","nPropDigits","CombinedUncertainty"],"CombinedUncertainty":{"tml_elements":["nCombUncertAssessNum","nCombExpandUncertValue"],"nCombExpandUncertValue":0.081,"nCombUncertAssessNum":1},"nPropValue":-8.013}],"VariableValue":[{"nVarValue":0.1305,"nVarDigits":4,"tml_elements":["nVarNumber","nVarValue","nVarDigits"],"nVarNumber":1},{"nVarValue":0.3871,"nVarNumber":2,"tml_elements":["nVarNumber","nVarValue","nVarDigits"],"nVarDigits":4}]},{"tml_elements":["VariableValue","PropertyValue"],"PropertyValue":[{"nPropNumber":1,"nPropDigits":4,"tml_elements":["nPropNumber","nPropValue","nPropDigits","CombinedUncertainty"],"CombinedUncertainty":{"tml_elements":["nCombUncertAssessNum","nCombExpandUncertValue"],"nCombExpandUncertValue":0.083,"nCombUncertAssessNum":1},"nPropValue":-8.221}],"VariableValue":[{"nVarValue":0.1332,"nVarNumber":1,"nVarDigits":4,"tml_elements":["nVarNumber","nVarValue","nVarDigits"]},{"nVarValue":0.4985,"tml_elements":["nVarNumber","nVarValue","nVarDigits"],"nVarDigits":4,"nVarNumber":2}]},{"VariableValue":[{"tml_elements":["nVarNumber","nVarValue","nVarDigits"],"nVarDigits":4,"nVarNumber":1,"nVarValue":0.1359},{"nVarNumber":2,"tml_elements":["nVarNumber","nVarValue","nVarDigits"],"nVarDigits":4,"nVarValue":0.362}],"PropertyValue":[{"nPropValue":-8.185,"CombinedUncertainty":{"tml_elements":["nCombUncertAssessNum","nCombExpandUncertValue"],"nCombExpandUncertValue":0.083,"nCombUncertAssessNum":1},"nPropNumber":1,"nPropDigits":4,"tml_elements":["nPropNumber","nPropValue","nPropDigits","CombinedUncertainty"]}],"tml_elements":["VariableValue","PropertyValue"]},{"PropertyValue":[{"tml_elements":["nPropNumber","nPropValue","nPropDigits","CombinedUncertainty"],"nPropDigits":4,"nPropNumber":1,"CombinedUncertainty":{"nCombExpandUncertValue":0.085,"tml_elements":["nCombUncertAssessNum","nCombExpandUncertValue"],"nCombUncertAssessNum":1},"nPropValue":-8.39}],"tml_elements":["VariableValue","PropertyValue"],"VariableValue":[{"nVarValue":0.137,"nVarDigits":4,"tml_elements":["nVarNumber","nVarValue","nVarDigits"],"nVarNumber":1},{"nVarValue":0.5127,"nVarDigits":4,"tml_elements":["nVarNumber","nVarValue","nVarDigits"],"nVarNumber":2}]},{"VariableValue":[{"nVarValue":0.1378,"nVarDigits":4,"tml_elements":["nVarNumber","nVarValue","nVarDigits"],"nVarNumber":1},{"nVarValue":0.2298,"nVarNumber":2,"nVarDigits":4,"tml_elements":["nVarNumber","nVarValue","nVarDigits"]}],"tml_elements":["VariableValue","PropertyValue"],"PropertyValue":[{"nPropNumber":1,"nPropDigits":4,"tml_elements":["nPropNumber","nPropValue","nPropDigits","CombinedUncertainty"],"CombinedUncertainty":{"tml_elements":["nCombUncertAssessNum","nCombExpandUncertValue"],"nCombExpandUncertValue":0.078,"nCombUncertAssessNum":1},"nPropValue":-7.659}]},{"tml_elements":["VariableValue","PropertyValue"],"PropertyValue":[{"nPropValue":-8.558,"CombinedUncertainty":{"tml_elements":["nCombUncertAssessNum","nCombExpandUncertValue"],"nCombExpandUncertValue":0.087,"nCombUncertAssessNum":1},"nPropNumber":1,"nPropDigits":4,"tml_elements":["nPropNumber","nPropValue","nPropDigits","CombinedUncertainty"]}],"VariableValue":[{"nVarValue":0.1408,"nVarNumber":1,"nVarDigits":4,"tml_elements":["nVarNumber","nVarValue","nVarDigits"]},{"nVarNumber":2,"tml_elements":["nVarNumber","nVarValue","nVarDigits"],"nVarDigits":4,"nVarValue":0.527}]},{"VariableValue":[{"nVarNumber":1,"tml_elements":["nVarNumber","nVarValue","nVarDigits"],"nVarDigits":4,"nVarValue":0.1415},{"tml_elements":["nVarNumber","nVarValue","nVarDigits"],"nVarDigits":4,"nVarNumber":2,"nVarValue":0.3355}],"PropertyValue":[{"nPropValue":-8.344,"CombinedUncertainty":{"nCombUncertAssessNum":1,"tml_elements":["nCombUncertAssessNum","nCombExpandUncertValue"],"nCombExpandUncertValue":0.084},"nPropNumber":1,"nPropDigits":4,"tml_elements":["nPropNumber","nPropValue","nPropDigits","CombinedUncertainty"]}],"tml_elements":["VariableValue","PropertyValue"]},{"PropertyValue":[{"CombinedUncertainty":{"nCombExpandUncertValue":0.083,"tml_elements":["nCombUncertAssessNum","nCombExpandUncertValue"],"nCombUncertAssessNum":1},"nPropValue":-8.167,"tml_elements":["nPropNumber","nPropValue","nPropDigits","CombinedUncertainty"],"nPropNumber":1,"nPropDigits":4}],"tml_elements":["VariableValue","PropertyValue"],"VariableValue":[{"nVarValue":0.1416,"nVarDigits":4,"tml_elements":["nVarNumber","nVarValue","nVarDigits"],"nVarNumber":1},{"nVarDigits":4,"tml_elements":["nVarNumber","nVarValue","nVarDigits"],"nVarNumber":2,"nVarValue":0.4194}]},{"PropertyValue":[{"tml_elements":["nPropNumber","nPropValue","nPropDigits","CombinedUncertainty"],"nPropNumber":1,"nPropDigits":4,"CombinedUncertainty":{"nCombUncertAssessNum":1,"nCombExpandUncertValue":0.088,"tml_elements":["nCombUncertAssessNum","nCombExpandUncertValue"]},"nPropValue":-8.708}],"tml_elements":["VariableValue","PropertyValue"],"VariableValue":[{"nVarDigits":4,"tml_elements":["nVarNumber","nVarValue","nVarDigits"],"nVarNumber":1,"nVarValue":0.1448},{"nVarDigits":4,"tml_elements":["nVarNumber","nVarValue","nVarDigits"],"nVarNumber":2,"nVarValue":0.5419}]},{"VariableValue":[{"nVarValue":0.1476,"nVarNumber":1,"tml_elements":["nVarNumber","nVarValue","nVarDigits"],"nVarDigits":4},{"tml_elements":["nVarNumber","nVarValue","nVarDigits"],"nVarDigits":4,"nVarNumber":2,"nVarValue":0.3068}],"PropertyValue":[{"nPropValue":-8.513,"CombinedUncertainty":{"nCombUncertAssessNum":1,"nCombExpandUncertValue":0.086,"tml_elements":["nCombUncertAssessNum","nCombExpandUncertValue"]},"tml_elements":["nPropNumber","nPropValue","nPropDigits","CombinedUncertainty"],"nPropNumber":1,"nPropDigits":4}],"tml_elements":["VariableValue","PropertyValue"]},{"VariableValue":[{"nVarValue":0.1488,"nVarNumber":1,"nVarDigits":4,"tml_elements":["nVarNumber","nVarValue","nVarDigits"]},{"nVarValue":0.5568,"tml_elements":["nVarNumber","nVarValue","nVarDigits"],"nVarDigits":4,"nVarNumber":2}],"PropertyValue":[{"tml_elements":["nPropNumber","nPropValue","nPropDigits","CombinedUncertainty"],"nPropNumber":1,"nPropDigits":4,"nPropValue":-8.89,"CombinedUncertainty":{"tml_elements":["nCombUncertAssessNum","nCombExpandUncertValue"],"nCombExpandUncertValue":0.09,"nCombUncertAssessNum":1}}],"tml_elements":["VariableValue","PropertyValue"]},{"VariableValue":[{"nVarNumber":1,"nVarDigits":4,"tml_elements":["nVarNumber","nVarValue","nVarDigits"],"nVarValue":0.1529},{"nVarNumber":2,"nVarDigits":4,"tml_elements":["nVarNumber","nVarValue","nVarDigits"],"nVarValue":0.5722}],"PropertyValue":[{"tml_elements":["nPropNumber","nPropValue","nPropDigits","CombinedUncertainty"],"nPropNumber":1,"nPropDigits":4,"CombinedUncertainty":{"nCombUncertAssessNum":1,"nCombExpandUncertValue":0.091,"tml_elements":["nCombUncertAssessNum","nCombExpandUncertValue"]},"nPropValue":-8.996}],"tml_elements":["VariableValue","PropertyValue"]},{"PropertyValue":[{"CombinedUncertainty":{"nCombUncertAssessNum":1,"nCombExpandUncertValue":0.088,"tml_elements":["nCombUncertAssessNum","nCombExpandUncertValue"]},"nPropValue":-8.689,"tml_elements":["nPropNumber","nPropValue","nPropDigits","CombinedUncertainty"],"nPropDigits":4,"nPropNumber":1}],"tml_elements":["VariableValue","PropertyValue"],"VariableValue":[{"tml_elements":["nVarNumber","nVarValue","nVarDigits"],"nVarDigits":4,"nVarNumber":1,"nVarValue":0.1535},{"nVarNumber":2,"tml_elements":["nVarNumber","nVarValue","nVarDigits"],"nVarDigits":4,"nVarValue":0.2793}]},{"VariableValue":[{"tml_elements":["nVarNumber","nVarValue","nVarDigits"],"nVarDigits":4,"nVarNumber":1,"nVarValue":0.157},{"nVarNumber":2,"tml_elements":["nVarNumber","nVarValue","nVarDigits"],"nVarDigits":4,"nVarValue":0.5874}],"PropertyValue":[{"nPropDigits":4,"nPropNumber":1,"tml_elements":["nPropNumber","nPropValue","nPropDigits","CombinedUncertainty"],"CombinedUncertainty":{"nCombUncertAssessNum":1,"nCombExpandUncertValue":0.092,"tml_elements":["nCombUncertAssessNum","nCombExpandUncertValue"]},"nPropValue":-9.126}],"tml_elements":["VariableValue","PropertyValue"]},{"PropertyValue":[{"CombinedUncertainty":{"nCombUncertAssessNum":1,"tml_elements":["nCombUncertAssessNum","nCombExpandUncertValue"],"nCombExpandUncertValue":0.089},"nPropValue":-8.813,"tml_elements":["nPropNumber","nPropValue","nPropDigits","CombinedUncertainty"],"nPropDigits":4,"nPropNumber":1}],"tml_elements":["VariableValue","PropertyValue"],"VariableValue":[{"nVarValue":0.1597,"nVarDigits":4,"tml_elements":["nVarNumber","nVarValue","nVarDigits"],"nVarNumber":1},{"nVarNumber":2,"tml_elements":["nVarNumber","nVarValue","nVarDigits"],"nVarDigits":4,"nVarValue":0.25}]},{"VariableValue":[{"nVarValue":0.1608,"nVarNumber":1,"tml_elements":["nVarNumber","nVarValue","nVarDigits"],"nVarDigits":4},{"nVarValue":0.6187,"tml_elements":["nVarNumber","nVarValue","nVarDigits"],"nVarDigits":4,"nVarNumber":2}],"tml_elements":["VariableValue","PropertyValue"],"PropertyValue":[{"nPropValue":-9.182,"CombinedUncertainty":{"nCombUncertAssessNum":1,"nCombExpandUncertValue":0.093,"tml_elements":["nCombUncertAssessNum","nCombExpandUncertValue"]},"tml_elements":["nPropNumber","nPropValue","nPropDigits","CombinedUncertainty"],"nPropNumber":1,"nPropDigits":4}]},{"PropertyValue":[{"nPropNumber":1,"nPropDigits":4,"tml_elements":["nPropNumber","nPropValue","nPropDigits","CombinedUncertainty"],"CombinedUncertainty":{"nCombUncertAssessNum":1,"nCombExpandUncertValue":0.094,"tml_elements":["nCombUncertAssessNum","nCombExpandUncertValue"]},"nPropValue":-9.321}],"tml_elements":["VariableValue","PropertyValue"],"VariableValue":[{"tml_elements":["nVarNumber","nVarValue","nVarDigits"],"nVarDigits":4,"nVarNumber":1,"nVarValue":0.1612},{"nVarNumber":2,"nVarDigits":4,"tml_elements":["nVarNumber","nVarValue","nVarDigits"],"nVarValue":0.6031}]},{"tml_elements":["VariableValue","PropertyValue"],"PropertyValue":[{"nPropDigits":4,"nPropNumber":1,"tml_elements":["nPropNumber","nPropValue","nPropDigits","CombinedUncertainty"],"nPropValue":-8.863,"CombinedUncertainty":{"nCombExpandUncertValue":0.09,"tml_elements":["nCombUncertAssessNum","nCombExpandUncertValue"],"nCombUncertAssessNum":1}}],"VariableValue":[{"nVarNumber":1,"tml_elements":["nVarNumber","nVarValue","nVarDigits"],"nVarDigits":4,"nVarValue":0.1636},{"nVarValue":0.2229,"tml_elements":["nVarNumber","nVarValue","nVarDigits"],"nVarDigits":4,"nVarNumber":2}]},{"tml_elements":["VariableValue","PropertyValue"],"PropertyValue":[{"tml_elements":["nPropNumber","nPropValue","nPropDigits","CombinedUncertainty"],"nPropNumber":1,"nPropDigits":4,"CombinedUncertainty":{"nCombUncertAssessNum":1,"nCombExpandUncertValue":0.096,"tml_elements":["nCombUncertAssessNum","nCombExpandUncertValue"]},"nPropValue":-9.465}],"VariableValue":[{"nVarValue":0.1655,"nVarNumber":1,"nVarDigits":4,"tml_elements":["nVarNumber","nVarValue","nVarDigits"]},{"nVarValue":0.6192,"nVarNumber":2,"tml_elements":["nVarNumber","nVarValue","nVarDigits"],"nVarDigits":4}]},{"VariableValue":[{"nVarNumber":1,"tml_elements":["nVarNumber","nVarValue","nVarDigits"],"nVarDigits":4,"nVarValue":0.1662},{"nVarValue":0.2195,"nVarNumber":2,"nVarDigits":4,"tml_elements":["nVarNumber","nVarValue","nVarDigits"]}],"PropertyValue":[{"tml_elements":["nPropNumber","nPropValue","nPropDigits","CombinedUncertainty"],"nPropDigits":4,"nPropNumber":1,"CombinedUncertainty":{"nCombUncertAssessNum":1,"nCombExpandUncertValue":0.091,"tml_elements":["nCombUncertAssessNum","nCombExpandUncertValue"]},"nPropValue":-8.989}],"tml_elements":["VariableValue","PropertyValue"]},{"VariableValue":[{"nVarDigits":4,"tml_elements":["nVarNumber","nVarValue","nVarDigits"],"nVarNumber":1,"nVarValue":0.1699},{"nVarValue":0.6358,"tml_elements":["nVarNumber","nVarValue","nVarDigits"],"nVarDigits":4,"nVarNumber":2}],"PropertyValue":[{"nPropNumber":1,"nPropDigits":4,"tml_elements":["nPropNumber","nPropValue","nPropDigits","CombinedUncertainty"],"CombinedUncertainty":{"nCombExpandUncertValue":0.097,"tml_elements":["nCombUncertAssessNum","nCombExpandUncertValue"],"nCombUncertAssessNum":1},"nPropValue":-9.61}],"tml_elements":["VariableValue","PropertyValue"]},{"VariableValue":[{"nVarValue":0.1726,"nVarDigits":4,"tml_elements":["nVarNumber","nVarValue","nVarDigits"],"nVarNumber":1},{"nVarDigits":4,"tml_elements":["nVarNumber","nVarValue","nVarDigits"],"nVarNumber":2,"nVarValue":0.1894}],"PropertyValue":[{"nPropValue":-9.156,"CombinedUncertainty":{"tml_elements":["nCombUncertAssessNum","nCombExpandUncertValue"],"nCombExpandUncertValue":0.093,"nCombUncertAssessNum":1},"tml_elements":["nPropNumber","nPropValue","nPropDigits","CombinedUncertainty"],"nPropDigits":4,"nPropNumber":1}],"tml_elements":["VariableValue","PropertyValue"]},{"VariableValue":[{"nVarNumber":1,"tml_elements":["nVarNumber","nVarValue","nVarDigits"],"nVarDigits":4,"nVarValue":0.1745},{"nVarDigits":4,"tml_elements":["nVarNumber","nVarValue","nVarDigits"],"nVarNumber":2,"nVarValue":0.6528}],"PropertyValue":[{"CombinedUncertainty":{"nCombExpandUncertValue":0.099,"tml_elements":["nCombUncertAssessNum","nCombExpandUncertValue"],"nCombUncertAssessNum":1},"nPropValue":-9.779,"tml_elements":["nPropNumber","nPropValue","nPropDigits","CombinedUncertainty"],"nPropNumber":1,"nPropDigits":4}],"tml_elements":["VariableValue","PropertyValue"]},{"tml_elements":["VariableValue","PropertyValue"],"PropertyValue":[{"nPropValue":-9.903,"CombinedUncertainty":{"tml_elements":["nCombUncertAssessNum","nCombExpandUncertValue"],"nCombExpandUncertValue":0.1,"nCombUncertAssessNum":1},"nPropNumber":1,"nPropDigits":4,"tml_elements":["nPropNumber","nPropValue","nPropDigits","CombinedUncertainty"]}],"VariableValue":[{"nVarValue":0.1792,"nVarNumber":1,"tml_elements":["nVarNumber","nVarValue","nVarDigits"],"nVarDigits":4},{"nVarDigits":4,"tml_elements":["nVarNumber","nVarValue","nVarDigits"],"nVarNumber":2,"nVarValue":0.6705}]},{"VariableValue":[{"nVarValue":0.1794,"nVarNumber":1,"tml_elements":["nVarNumber","nVarValue","nVarDigits"],"nVarDigits":4},{"nVarValue":0.1575,"nVarNumber":2,"nVarDigits":4,"tml_elements":["nVarNumber","nVarValue","nVarDigits"]}],"PropertyValue":[{"nPropValue":-9.341,"CombinedUncertainty":{"nCombUncertAssessNum":1,"nCombExpandUncertValue":0.094,"tml_elements":["nCombUncertAssessNum","nCombExpandUncertValue"]},"nPropNumber":1,"nPropDigits":4,"tml_elements":["nPropNumber","nPropValue","nPropDigits","CombinedUncertainty"]}],"tml_elements":["VariableValue","PropertyValue"]},{"VariableValue":[{"nVarNumber":1,"tml_elements":["nVarNumber","nVarValue","nVarDigits"],"nVarDigits":4,"nVarValue":0.1842},{"nVarNumber":2,"nVarDigits":4,"tml_elements":["nVarNumber","nVarValue","nVarDigits"],"nVarValue":0.6892}],"PropertyValue":[{"tml_elements":["nPropNumber","nPropValue","nPropDigits","CombinedUncertainty"],"nPropDigits":5,"nPropNumber":1,"nPropValue":-10.064,"CombinedUncertainty":{"nCombUncertAssessNum":1,"tml_elements":["nCombUncertAssessNum","nCombExpandUncertValue"],"nCombExpandUncertValue":0.102}}],"tml_elements":["VariableValue","PropertyValue"]},{"PropertyValue":[{"CombinedUncertainty":{"nCombUncertAssessNum":1,"nCombExpandUncertValue":0.095,"tml_elements":["nCombUncertAssessNum","nCombExpandUncertValue"]},"nPropValue":-9.432,"tml_elements":["nPropNumber","nPropValue","nPropDigits","CombinedUncertainty"],"nPropDigits":4,"nPropNumber":1}],"tml_elements":["VariableValue","PropertyValue"],"VariableValue":[{"nVarValue":0.1848,"nVarNumber":1,"tml_elements":["nVarNumber","nVarValue","nVarDigits"],"nVarDigits":4},{"nVarValue":0.1321,"tml_elements":["nVarNumber","nVarValue","nVarDigits"],"nVarDigits":4,"nVarNumber":2}]},{"PropertyValue":[{"CombinedUncertainty":{"tml_elements":["nCombUncertAssessNum","nCombExpandUncertValue"],"nCombExpandUncertValue":0.104,"nCombUncertAssessNum":1},"nPropValue":-10.286,"tml_elements":["nPropNumber","nPropValue","nPropDigits","CombinedUncertainty"],"nPropNumber":1,"nPropDigits":5}],"tml_elements":["VariableValue","PropertyValue"],"VariableValue":[{"nVarValue":0.1856,"nVarNumber":1,"tml_elements":["nVarNumber","nVarValue","nVarDigits"],"nVarDigits":4},{"nVarDigits":4,"tml_elements":["nVarNumber","nVarValue","nVarDigits"],"nVarNumber":2,"nVarValue":0.3979}]},{"VariableValue":[{"nVarValue":0.1893,"nVarDigits":4,"tml_elements":["nVarNumber","nVarValue","nVarDigits"],"nVarNumber":1},{"nVarDigits":4,"tml_elements":["nVarNumber","nVarValue","nVarDigits"],"nVarNumber":2,"nVarValue":0.7083}],"tml_elements":["VariableValue","PropertyValue"],"PropertyValue":[{"nPropDigits":5,"nPropNumber":1,"tml_elements":["nPropNumber","nPropValue","nPropDigits","CombinedUncertainty"],"nPropValue":-10.265,"CombinedUncertainty":{"nCombExpandUncertValue":0.104,"tml_elements":["nCombUncertAssessNum","nCombExpandUncertValue"],"nCombUncertAssessNum":1}}]},{"VariableValue":[{"nVarNumber":1,"nVarDigits":4,"tml_elements":["nVarNumber","nVarValue","nVarDigits"],"nVarValue":0.1897},{"nVarDigits":4,"tml_elements":["nVarNumber","nVarValue","nVarDigits"],"nVarNumber":2,"nVarValue":0.2159}],"PropertyValue":[{"CombinedUncertainty":{"tml_elements":["nCombUncertAssessNum","nCombExpandUncertValue"],"nCombExpandUncertValue":0.102,"nCombUncertAssessNum":1},"nPropValue":-10.086,"tml_elements":["nPropNumber","nPropValue","nPropDigits","CombinedUncertainty"],"nPropDigits":5,"nPropNumber":1}],"tml_elements":["VariableValue","PropertyValue"]},{"VariableValue":[{"nVarNumber":1,"tml_elements":["nVarNumber","nVarValue","nVarDigits"],"nVarDigits":4,"nVarValue":0.1904},{"nVarValue":0.1059,"nVarNumber":2,"tml_elements":["nVarNumber","nVarValue","nVarDigits"],"nVarDigits":4}],"tml_elements":["VariableValue","PropertyValue"],"PropertyValue":[{"tml_elements":["nPropNumber","nPropValue","nPropDigits","CombinedUncertainty"],"nPropNumber":1,"nPropDigits":4,"CombinedUncertainty":{"nCombUncertAssessNum":1,"tml_elements":["nCombUncertAssessNum","nCombExpandUncertValue"],"nCombExpandUncertValue":0.096},"nPropValue":-9.5}]},{"VariableValue":[{"nVarValue":0.1935,"nVarNumber":1,"tml_elements":["nVarNumber","nVarValue","nVarDigits"],"nVarDigits":4},{"nVarValue":0.5945,"nVarNumber":2,"nVarDigits":4,"tml_elements":["nVarNumber","nVarValue","nVarDigits"]}],"tml_elements":["VariableValue","PropertyValue"],"PropertyValue":[{"nPropNumber":1,"nPropDigits":5,"tml_elements":["nPropNumber","nPropValue","nPropDigits","CombinedUncertainty"],"CombinedUncertainty":{"nCombUncertAssessNum":1,"nCombExpandUncertValue":0.109,"tml_elements":["nCombUncertAssessNum","nCombExpandUncertValue"]},"nPropValue":-10.834}]},{"PropertyValue":[{"CombinedUncertainty":{"nCombUncertAssessNum":1,"nCombExpandUncertValue":0.105,"tml_elements":["nCombUncertAssessNum","nCombExpandUncertValue"]},"nPropValue":-10.447,"tml_elements":["nPropNumber","nPropValue","nPropDigits","CombinedUncertainty"],"nPropDigits":5,"nPropNumber":1}],"tml_elements":["VariableValue","PropertyValue"],"VariableValue":[{"nVarValue":0.1946,"tml_elements":["nVarNumber","nVarValue","nVarDigits"],"nVarDigits":4,"nVarNumber":1},{"nVarNumber":2,"nVarDigits":4,"tml_elements":["nVarNumber","nVarValue","nVarDigits"],"nVarValue":0.7283}]},{"tml_elements":["VariableValue","PropertyValue"],"PropertyValue":[{"tml_elements":["nPropNumber","nPropValue","nPropDigits","CombinedUncertainty"],"nPropNumber":1,"nPropDigits":4,"CombinedUncertainty":{"nCombUncertAssessNum":1,"nCombExpandUncertValue":0.096,"tml_elements":["nCombUncertAssessNum","nCombExpandUncertValue"]},"nPropValue":-9.542}],"VariableValue":[{"nVarDigits":4,"tml_elements":["nVarNumber","nVarValue","nVarDigits"],"nVarNumber":1,"nVarValue":0.196},{"nVarNumber":2,"tml_elements":["nVarNumber","nVarValue","nVarDigits"],"nVarDigits":3,"nVarValue":0.0796}]},{"VariableValue":[{"nVarValue":0.1999,"nVarNumber":1,"nVarDigits":4,"tml_elements":["nVarNumber","nVarValue","nVarDigits"]},{"nVarValue":0.748,"nVarNumber":2,"tml_elements":["nVarNumber","nVarValue","nVarDigits"],"nVarDigits":4}],"PropertyValue":[{"nPropValue":-10.582,"CombinedUncertainty":{"tml_elements":["nCombUncertAssessNum","nCombExpandUncertValue"],"nCombExpandUncertValue":0.107,"nCombUncertAssessNum":1},"nPropDigits":5,"nPropNumber":1,"tml_elements":["nPropNumber","nPropValue","nPropDigits","CombinedUncertainty"]}],"tml_elements":["VariableValue","PropertyValue"]},{"PropertyValue":[{"CombinedUncertainty":{"nCombExpandUncertValue":0.097,"tml_elements":["nCombUncertAssessNum","nCombExpandUncertValue"],"nCombUncertAssessNum":1},"nPropValue":-9.57,"nPropDigits":4,"nPropNumber":1,"tml_elements":["nPropNumber","nPropValue","nPropDigits","CombinedUncertainty"]}],"tml_elements":["VariableValue","PropertyValue"],"VariableValue":[{"nVarValue":0.2017,"nVarDigits":4,"tml_elements":["nVarNumber","nVarValue","nVarDigits"],"nVarNumber":1},{"nVarValue":0.0527,"nVarNumber":2,"nVarDigits":3,"tml_elements":["nVarNumber","nVarValue","nVarDigits"]}]},{"VariableValue":[{"nVarNumber":1,"tml_elements":["nVarNumber","nVarValue","nVarDigits"],"nVarDigits":4,"nVarValue":0.2054},{"nVarValue":0.7684,"nVarNumber":2,"nVarDigits":4,"tml_elements":["nVarNumber","nVarValue","nVarDigits"]}],"PropertyValue":[{"tml_elements":["nPropNumber","nPropValue","nPropDigits","CombinedUncertainty"],"nPropNumber":1,"nPropDigits":5,"nPropValue":-10.687,"CombinedUncertainty":{"nCombUncertAssessNum":1,"nCombExpandUncertValue":0.108,"tml_elements":["nCombUncertAssessNum","nCombExpandUncertValue"]}}],"tml_elements":["VariableValue","PropertyValue"]},{"tml_elements":["VariableValue","PropertyValue"],"PropertyValue":[{"tml_elements":["nPropNumber","nPropValue","nPropDigits","CombinedUncertainty"],"nPropDigits":4,"nPropNumber":1,"CombinedUncertainty":{"nCombExpandUncertValue":0.097,"tml_elements":["nCombUncertAssessNum","nCombExpandUncertValue"],"nCombUncertAssessNum":1},"nPropValue":-9.558}],"VariableValue":[{"nVarDigits":4,"tml_elements":["nVarNumber","nVarValue","nVarDigits"],"nVarNumber":1,"nVarValue":0.2073},{"tml_elements":["nVarNumber","nVarValue","nVarDigits"],"nVarDigits":3,"nVarNumber":2,"nVarValue":0.0267}]},{"VariableValue":[{"nVarValue":0.2109,"nVarDigits":4,"tml_elements":["nVarNumber","nVarValue","nVarDigits"],"nVarNumber":1},{"nVarNumber":2,"nVarDigits":4,"tml_elements":["nVarNumber","nVarValue","nVarDigits"],"nVarValue":0.7891}],"PropertyValue":[{"tml_elements":["nPropNumber","nPropValue","nPropDigits","CombinedUncertainty"],"nPropDigits":5,"nPropNumber":1,"CombinedUncertainty":{"nCombExpandUncertValue":0.109,"tml_elements":["nCombUncertAssessNum","nCombExpandUncertValue"],"nCombUncertAssessNum":1},"nPropValue":-10.782}],"tml_elements":["VariableValue","PropertyValue"]},{"VariableValue":[{"nVarValue":0.213,"nVarNumber":1,"tml_elements":["nVarNumber","nVarValue","nVarDigits"],"nVarDigits":4},{"nVarDigits":2,"tml_elements":["nVarNumber","nVarValue","nVarDigits"],"nVarNumber":2,"nVarValue":0}],"tml_elements":["VariableValue","PropertyValue"],"PropertyValue":[{"tml_elements":["nPropNumber","nPropValue","nPropDigits","CombinedUncertainty"],"nPropNumber":1,"nPropDigits":4,"CombinedUncertainty":{"nCombUncertAssessNum":1,"nCombExpandUncertValue":0.097,"tml_elements":["nCombUncertAssessNum","nCombExpandUncertValue"]},"nPropValue":-9.592}]},{"PropertyValue":[{"CombinedUncertainty":{"nCombUncertAssessNum":1,"tml_elements":["nCombUncertAssessNum","nCombExpandUncertValue"],"nCombExpandUncertValue":0.115},"nPropValue":-11.362,"nPropNumber":1,"nPropDigits":5,"tml_elements":["nPropNumber","nPropValue","nPropDigits","CombinedUncertainty"]}],"tml_elements":["VariableValue","PropertyValue"],"VariableValue":[{"nVarNumber":1,"tml_elements":["nVarNumber","nVarValue","nVarDigits"],"nVarDigits":4,"nVarValue":0.2169},{"nVarValue":0.2087,"nVarDigits":4,"tml_elements":["nVarNumber","nVarValue","nVarDigits"],"nVarNumber":2}]},{"VariableValue":[{"nVarValue":0.2244,"nVarDigits":4,"tml_elements":["nVarNumber","nVarValue","nVarDigits"],"nVarNumber":1},{"nVarValue":0.5718,"nVarNumber":2,"tml_elements":["nVarNumber","nVarValue","nVarDigits"],"nVarDigits":4}],"PropertyValue":[{"nPropValue":-12.359,"CombinedUncertainty":{"tml_elements":["nCombUncertAssessNum","nCombExpandUncertValue"],"nCombExpandUncertValue":0.125,"nCombUncertAssessNum":1},"nPropDigits":5,"nPropNumber":1,"tml_elements":["nPropNumber","nPropValue","nPropDigits","CombinedUncertainty"]}],"tml_elements":["VariableValue","PropertyValue"]},{"PropertyValue":[{"nPropDigits":5,"nPropNumber":1,"tml_elements":["nPropNumber","nPropValue","nPropDigits","CombinedUncertainty"],"nPropValue":-12.287,"CombinedUncertainty":{"nCombUncertAssessNum":1,"tml_elements":["nCombUncertAssessNum","nCombExpandUncertValue"],"nCombExpandUncertValue":0.124}}],"tml_elements":["VariableValue","PropertyValue"],"VariableValue":[{"nVarValue":0.2282,"nVarNumber":1,"nVarDigits":4,"tml_elements":["nVarNumber","nVarValue","nVarDigits"]},{"nVarValue":0.3771,"nVarNumber":2,"nVarDigits":4,"tml_elements":["nVarNumber","nVarValue","nVarDigits"]}]},{"VariableValue":[{"nVarNumber":1,"tml_elements":["nVarNumber","nVarValue","nVarDigits"],"nVarDigits":4,"nVarValue":0.2431},{"nVarNumber":2,"nVarDigits":4,"tml_elements":["nVarNumber","nVarValue","nVarDigits"],"nVarValue":0.2017}],"PropertyValue":[{"nPropNumber":1,"nPropDigits":5,"tml_elements":["nPropNumber","nPropValue","nPropDigits","CombinedUncertainty"],"CombinedUncertainty":{"tml_elements":["nCombUncertAssessNum","nCombExpandUncertValue"],"nCombExpandUncertValue":0.127,"nCombUncertAssessNum":1},"nPropValue":-12.578}],"tml_elements":["VariableValue","PropertyValue"]},{"VariableValue":[{"nVarValue":0.2532,"tml_elements":["nVarNumber","nVarValue","nVarDigits"],"nVarDigits":4,"nVarNumber":1},{"nVarNumber":2,"nVarDigits":4,"tml_elements":["nVarNumber","nVarValue","nVarDigits"],"nVarValue":0.5506}],"PropertyValue":[{"nPropValue":-13.748,"CombinedUncertainty":{"tml_elements":["nCombUncertAssessNum","nCombExpandUncertValue"],"nCombExpandUncertValue":0.138,"nCombUncertAssessNum":1},"tml_elements":["nPropNumber","nPropValue","nPropDigits","CombinedUncertainty"],"nPropNumber":1,"nPropDigits":5}],"tml_elements":["VariableValue","PropertyValue"]},{"PropertyValue":[{"CombinedUncertainty":{"nCombUncertAssessNum":1,"nCombExpandUncertValue":0.142,"tml_elements":["nCombUncertAssessNum","nCombExpandUncertValue"]},"nPropValue":-14.085,"nPropDigits":5,"nPropNumber":1,"tml_elements":["nPropNumber","nPropValue","nPropDigits","CombinedUncertainty"]}],"tml_elements":["VariableValue","PropertyValue"],"VariableValue":[{"nVarNumber":1,"nVarDigits":4,"tml_elements":["nVarNumber","nVarValue","nVarDigits"],"nVarValue":0.2669},{"nVarValue":0.3582,"nVarNumber":2,"tml_elements":["nVarNumber","nVarValue","nVarDigits"],"nVarDigits":4}]},{"tml_elements":["VariableValue","PropertyValue"],"PropertyValue":[{"nPropValue":-13.738,"CombinedUncertainty":{"nCombUncertAssessNum":1,"tml_elements":["nCombUncertAssessNum","nCombExpandUncertValue"],"nCombExpandUncertValue":0.138},"nPropNumber":1,"nPropDigits":5,"tml_elements":["nPropNumber","nPropValue","nPropDigits","CombinedUncertainty"]}],"VariableValue":[{"nVarValue":0.268,"nVarNumber":1,"tml_elements":["nVarNumber","nVarValue","nVarDigits"],"nVarDigits":4},{"nVarNumber":2,"tml_elements":["nVarNumber","nVarValue","nVarDigits"],"nVarDigits":4,"nVarValue":0.1951}]},{"tml_elements":["VariableValue","PropertyValue"],"PropertyValue":[{"nPropNumber":1,"nPropDigits":5,"tml_elements":["nPropNumber","nPropValue","nPropDigits","CombinedUncertainty"],"CombinedUncertainty":{"nCombUncertAssessNum":1,"tml_elements":["nCombUncertAssessNum","nCombExpandUncertValue"],"nCombExpandUncertValue":0.152},"nPropValue":-15.123}],"VariableValue":[{"nVarValue":0.2803,"nVarDigits":4,"tml_elements":["nVarNumber","nVarValue","nVarDigits"],"nVarNumber":1},{"nVarValue":0.5305,"nVarDigits":4,"tml_elements":["nVarNumber","nVarValue","nVarDigits"],"nVarNumber":2}]},{"VariableValue":[{"nVarValue":0.2919,"nVarNumber":1,"tml_elements":["nVarNumber","nVarValue","nVarDigits"],"nVarDigits":4},{"nVarNumber":2,"nVarDigits":4,"tml_elements":["nVarNumber","nVarValue","nVarDigits"],"nVarValue":0.1887}],"PropertyValue":[{"tml_elements":["nPropNumber","nPropValue","nPropDigits","CombinedUncertainty"],"nPropDigits":5,"nPropNumber":1,"nPropValue":-14.765,"CombinedUncertainty":{"nCombUncertAssessNum":1,"nCombExpandUncertValue":0.149,"tml_elements":["nCombUncertAssessNum","nCombExpandUncertValue"]}}],"tml_elements":["VariableValue","PropertyValue"]},{"tml_elements":["VariableValue","PropertyValue"],"PropertyValue":[{"CombinedUncertainty":{"tml_elements":["nCombUncertAssessNum","nCombExpandUncertValue"],"nCombExpandUncertValue":0.159,"nCombUncertAssessNum":1},"nPropValue":-15.821,"tml_elements":["nPropNumber","nPropValue","nPropDigits","CombinedUncertainty"],"nPropDigits":5,"nPropNumber":1}],"VariableValue":[{"nVarValue":0.3024,"nVarNumber":1,"tml_elements":["nVarNumber","nVarValue","nVarDigits"],"nVarDigits":4},{"tml_elements":["nVarNumber","nVarValue","nVarDigits"],"nVarDigits":4,"nVarNumber":2,"nVarValue":0.3409}]},{"VariableValue":[{"nVarNumber":1,"nVarDigits":4,"tml_elements":["nVarNumber","nVarValue","nVarDigits"],"nVarValue":0.3059},{"nVarNumber":2,"tml_elements":["nVarNumber","nVarValue","nVarDigits"],"nVarDigits":4,"nVarValue":0.5117}],"tml_elements":["VariableValue","PropertyValue"],"PropertyValue":[{"nPropDigits":5,"nPropNumber":1,"tml_elements":["nPropNumber","nPropValue","nPropDigits","CombinedUncertainty"],"CombinedUncertainty":{"tml_elements":["nCombUncertAssessNum","nCombExpandUncertValue"],"nCombExpandUncertValue":0.169,"nCombUncertAssessNum":1},"nPropValue":-16.798}]},{"tml_elements":["VariableValue","PropertyValue"],"PropertyValue":[{"nPropValue":-15.582,"CombinedUncertainty":{"nCombUncertAssessNum":1,"nCombExpandUncertValue":0.157,"tml_elements":["nCombUncertAssessNum","nCombExpandUncertValue"]},"nPropNumber":1,"nPropDigits":5,"tml_elements":["nPropNumber","nPropValue","nPropDigits","CombinedUncertainty"]}],"VariableValue":[{"nVarNumber":1,"tml_elements":["nVarNumber","nVarValue","nVarDigits"],"nVarDigits":4,"nVarValue":0.3148},{"nVarDigits":4,"tml_elements":["nVarNumber","nVarValue","nVarDigits"],"nVarNumber":2,"nVarValue":0.1826}]},{"VariableValue":[{"nVarDigits":4,"tml_elements":["nVarNumber","nVarValue","nVarDigits"],"nVarNumber":1,"nVarValue":0.3299},{"nVarDigits":4,"tml_elements":["nVarNumber","nVarValue","nVarDigits"],"nVarNumber":2,"nVarValue":0.494}],"tml_elements":["VariableValue","PropertyValue"],"PropertyValue":[{"nPropNumber":1,"nPropDigits":5,"tml_elements":["nPropNumber","nPropValue","nPropDigits","CombinedUncertainty"],"nPropValue":-18.186,"CombinedUncertainty":{"nCombExpandUncertValue":0.183,"tml_elements":["nCombUncertAssessNum","nCombExpandUncertValue"],"nCombUncertAssessNum":1}}]},{"tml_elements":["VariableValue","PropertyValue"],"PropertyValue":[{"nPropValue":-17.291,"CombinedUncertainty":{"tml_elements":["nCombUncertAssessNum","nCombExpandUncertValue"],"nCombExpandUncertValue":0.174,"nCombUncertAssessNum":1},"nPropDigits":5,"nPropNumber":1,"tml_elements":["nPropNumber","nPropValue","nPropDigits","CombinedUncertainty"]}],"VariableValue":[{"nVarValue":0.3349,"nVarNumber":1,"tml_elements":["nVarNumber","nVarValue","nVarDigits"],"nVarDigits":4},{"nVarValue":0.325,"nVarNumber":2,"nVarDigits":4,"tml_elements":["nVarNumber","nVarValue","nVarDigits"]}]},{"VariableValue":[{"nVarNumber":1,"nVarDigits":4,"tml_elements":["nVarNumber","nVarValue","nVarDigits"],"nVarValue":0.3363},{"nVarValue":0.1769,"nVarNumber":2,"nVarDigits":4,"tml_elements":["nVarNumber","nVarValue","nVarDigits"]}],"PropertyValue":[{"CombinedUncertainty":{"tml_elements":["nCombUncertAssessNum","nCombExpandUncertValue"],"nCombExpandUncertValue":0.164,"nCombUncertAssessNum":1},"nPropValue":-16.317,"tml_elements":["nPropNumber","nPropValue","nPropDigits","CombinedUncertainty"],"nPropNumber":1,"nPropDigits":5}],"tml_elements":["VariableValue","PropertyValue"]},{"VariableValue":[{"nVarValue":0.3524,"nVarNumber":1,"nVarDigits":4,"tml_elements":["nVarNumber","nVarValue","nVarDigits"]},{"nVarValue":0.4774,"nVarNumber":2,"tml_elements":["nVarNumber","nVarValue","nVarDigits"],"nVarDigits":4}],"tml_elements":["VariableValue","PropertyValue"],"PropertyValue":[{"CombinedUncertainty":{"tml_elements":["nCombUncertAssessNum","nCombExpandUncertValue"],"nCombExpandUncertValue":0.199,"nCombUncertAssessNum":1},"nPropValue":-19.797,"nPropNumber":1,"nPropDigits":5,"tml_elements":["nPropNumber","nPropValue","nPropDigits","CombinedUncertainty"]}]},{"VariableValue":[{"nVarDigits":4,"tml_elements":["nVarNumber","nVarValue","nVarDigits"],"nVarNumber":1,"nVarValue":0.3575},{"nVarValue":0.1712,"nVarNumber":2,"nVarDigits":4,"tml_elements":["nVarNumber","nVarValue","nVarDigits"]}],"tml_elements":["VariableValue","PropertyValue"],"PropertyValue":[{"CombinedUncertainty":{"nCombUncertAssessNum":1,"nCombExpandUncertValue":0.17,"tml_elements":["nCombUncertAssessNum","nCombExpandUncertValue"]},"nPropValue":-16.861,"nPropDigits":5,"nPropNumber":1,"tml_elements":["nPropNumber","nPropValue","nPropDigits","CombinedUncertainty"]}]},{"PropertyValue":[{"CombinedUncertainty":{"nCombExpandUncertValue":0.189,"tml_elements":["nCombUncertAssessNum","nCombExpandUncertValue"],"nCombUncertAssessNum":1},"nPropValue":-18.84,"nPropDigits":5,"nPropNumber":1,"tml_elements":["nPropNumber","nPropValue","nPropDigits","CombinedUncertainty"]}],"tml_elements":["VariableValue","PropertyValue"],"VariableValue":[{"nVarDigits":4,"tml_elements":["nVarNumber","nVarValue","nVarDigits"],"nVarNumber":1,"nVarValue":0.3648},{"nVarValue":0.3104,"tml_elements":["nVarNumber","nVarValue","nVarDigits"],"nVarDigits":4,"nVarNumber":2}]},{"tml_elements":["VariableValue","PropertyValue"],"PropertyValue":[{"CombinedUncertainty":{"nCombUncertAssessNum":1,"tml_elements":["nCombUncertAssessNum","nCombExpandUncertValue"],"nCombExpandUncertValue":0.215},"nPropValue":-21.357,"nPropNumber":1,"nPropDigits":5,"tml_elements":["nPropNumber","nPropValue","nPropDigits","CombinedUncertainty"]}],"VariableValue":[{"tml_elements":["nVarNumber","nVarValue","nVarDigits"],"nVarDigits":4,"nVarNumber":1,"nVarValue":0.3736},{"nVarNumber":2,"tml_elements":["nVarNumber","nVarValue","nVarDigits"],"nVarDigits":4,"nVarValue":0.4618}]},{"VariableValue":[{"tml_elements":["nVarNumber","nVarValue","nVarDigits"],"nVarDigits":4,"nVarNumber":1,"nVarValue":0.3774},{"nVarDigits":4,"tml_elements":["nVarNumber","nVarValue","nVarDigits"],"nVarNumber":2,"nVarValue":0.1659}],"PropertyValue":[{"CombinedUncertainty":{"nCombUncertAssessNum":1,"tml_elements":["nCombUncertAssessNum","nCombExpandUncertValue"],"nCombExpandUncertValue":0.177},"nPropValue":-17.571,"nPropDigits":5,"nPropNumber":1,"tml_elements":["nPropNumber","nPropValue","nPropDigits","CombinedUncertainty"]}],"tml_elements":["VariableValue","PropertyValue"]},{"tml_elements":["VariableValue","PropertyValue"],"PropertyValue":[{"nPropNumber":1,"nPropDigits":5,"tml_elements":["nPropNumber","nPropValue","nPropDigits","CombinedUncertainty"],"CombinedUncertainty":{"nCombExpandUncertValue":0.206,"tml_elements":["nCombUncertAssessNum","nCombExpandUncertValue"],"nCombUncertAssessNum":1},"nPropValue":-20.524}],"VariableValue":[{"nVarNumber":1,"nVarDigits":4,"tml_elements":["nVarNumber","nVarValue","nVarDigits"],"nVarValue":0.3928},{"nVarValue":0.2967,"nVarDigits":4,"tml_elements":["nVarNumber","nVarValue","nVarDigits"],"nVarNumber":2}]},{"tml_elements":["VariableValue","PropertyValue"],"PropertyValue":[{"nPropValue":-22.411,"CombinedUncertainty":{"nCombUncertAssessNum":1,"tml_elements":["nCombUncertAssessNum","nCombExpandUncertValue"],"nCombExpandUncertValue":0.225},"nPropNumber":1,"nPropDigits":5,"tml_elements":["nPropNumber","nPropValue","nPropDigits","CombinedUncertainty"]}],"VariableValue":[{"tml_elements":["nVarNumber","nVarValue","nVarDigits"],"nVarDigits":4,"nVarNumber":1,"nVarValue":0.3936},{"nVarNumber":2,"nVarDigits":4,"tml_elements":["nVarNumber","nVarValue","nVarDigits"],"nVarValue":0.4471}]},{"tml_elements":["VariableValue","PropertyValue"],"PropertyValue":[{"nPropDigits":5,"nPropNumber":1,"tml_elements":["nPropNumber","nPropValue","nPropDigits","CombinedUncertainty"],"nPropValue":-18.099,"CombinedUncertainty":{"nCombUncertAssessNum":1,"nCombExpandUncertValue":0.182,"tml_elements":["nCombUncertAssessNum","nCombExpandUncertValue"]}}],"VariableValue":[{"nVarDigits":4,"tml_elements":["nVarNumber","nVarValue","nVarDigits"],"nVarNumber":1,"nVarValue":0.3964},{"nVarValue":0.1609,"nVarNumber":2,"tml_elements":["nVarNumber","nVarValue","nVarDigits"],"nVarDigits":4}]},{"VariableValue":[{"nVarDigits":4,"tml_elements":["nVarNumber","nVarValue","nVarDigits"],"nVarNumber":1,"nVarValue":0.413},{"nVarValue":0.4327,"tml_elements":["nVarNumber","nVarValue","nVarDigits"],"nVarDigits":4,"nVarNumber":2}],"tml_elements":["VariableValue","PropertyValue"],"PropertyValue":[{"nPropNumber":1,"nPropDigits":5,"tml_elements":["nPropNumber","nPropValue","nPropDigits","CombinedUncertainty"],"nPropValue":-23.548,"CombinedUncertainty":{"nCombUncertAssessNum":1,"nCombExpandUncertValue":0.236,"tml_elements":["nCombUncertAssessNum","nCombExpandUncertValue"]}}]},{"VariableValue":[{"nVarValue":0.4149,"nVarNumber":1,"nVarDigits":4,"tml_elements":["nVarNumber","nVarValue","nVarDigits"]},{"nVarValue":0.1559,"nVarNumber":2,"nVarDigits":4,"tml_elements":["nVarNumber","nVarValue","nVarDigits"]}],"PropertyValue":[{"tml_elements":["nPropNumber","nPropValue","nPropDigits","CombinedUncertainty"],"nPropDigits":5,"nPropNumber":1,"CombinedUncertainty":{"nCombExpandUncertValue":0.187,"tml_elements":["nCombUncertAssessNum","nCombExpandUncertValue"],"nCombUncertAssessNum":1},"nPropValue":-18.639}],"tml_elements":["VariableValue","PropertyValue"]},{"VariableValue":[{"nVarValue":0.4186,"nVarNumber":1,"tml_elements":["nVarNumber","nVarValue","nVarDigits"],"nVarDigits":4},{"tml_elements":["nVarNumber","nVarValue","nVarDigits"],"nVarDigits":4,"nVarNumber":2,"nVarValue":0.2841}],"tml_elements":["VariableValue","PropertyValue"],"PropertyValue":[{"tml_elements":["nPropNumber","nPropValue","nPropDigits","CombinedUncertainty"],"nPropNumber":1,"nPropDigits":5,"CombinedUncertainty":{"nCombUncertAssessNum":1,"nCombExpandUncertValue":0.218,"tml_elements":["nCombUncertAssessNum","nCombExpandUncertValue"]},"nPropValue":-21.736}]},{"tml_elements":["VariableValue","PropertyValue"],"PropertyValue":[{"nPropNumber":1,"nPropDigits":5,"tml_elements":["nPropNumber","nPropValue","nPropDigits","CombinedUncertainty"],"CombinedUncertainty":{"tml_elements":["nCombUncertAssessNum","nCombExpandUncertValue"],"nCombExpandUncertValue":0.246,"nCombUncertAssessNum":1},"nPropValue":-24.524}],"VariableValue":[{"nVarNumber":1,"nVarDigits":4,"tml_elements":["nVarNumber","nVarValue","nVarDigits"],"nVarValue":0.4313},{"tml_elements":["nVarNumber","nVarValue","nVarDigits"],"nVarDigits":4,"nVarNumber":2,"nVarValue":0.4193}]},{"VariableValue":[{"nVarValue":0.4326,"nVarDigits":4,"tml_elements":["nVarNumber","nVarValue","nVarDigits"],"nVarNumber":1},{"tml_elements":["nVarNumber","nVarValue","nVarDigits"],"nVarDigits":4,"nVarNumber":2,"nVarValue":0.1512}],"PropertyValue":[{"tml_elements":["nPropNumber","nPropValue","nPropDigits","CombinedUncertainty"],"nPropDigits":5,"nPropNumber":1,"CombinedUncertainty":{"nCombExpandUncertValue":0.193,"tml_elements":["nCombUncertAssessNum","nCombExpandUncertValue"],"nCombUncertAssessNum":1},"nPropValue":-19.155}],"tml_elements":["VariableValue","PropertyValue"]},{"PropertyValue":[{"nPropValue":-22.373,"CombinedUncertainty":{"nCombExpandUncertValue":0.225,"tml_elements":["nCombUncertAssessNum","nCombExpandUncertValue"],"nCombUncertAssessNum":1},"nPropDigits":5,"nPropNumber":1,"tml_elements":["nPropNumber","nPropValue","nPropDigits","CombinedUncertainty"]}],"tml_elements":["VariableValue","PropertyValue"],"VariableValue":[{"nVarDigits":4,"tml_elements":["nVarNumber","nVarValue","nVarDigits"],"nVarNumber":1,"nVarValue":0.4426},{"nVarDigits":4,"tml_elements":["nVarNumber","nVarValue","nVarDigits"],"nVarNumber":2,"nVarValue":0.2723}]},{"PropertyValue":[{"nPropValue":-19.628,"CombinedUncertainty":{"nCombUncertAssessNum":1,"nCombExpandUncertValue":0.197,"tml_elements":["nCombUncertAssessNum","nCombExpandUncertValue"]},"nPropDigits":5,"nPropNumber":1,"tml_elements":["nPropNumber","nPropValue","nPropDigits","CombinedUncertainty"]}],"tml_elements":["VariableValue","PropertyValue"],"VariableValue":[{"nVarValue":0.4493,"nVarNumber":1,"tml_elements":["nVarNumber","nVarValue","nVarDigits"],"nVarDigits":4},{"nVarNumber":2,"tml_elements":["nVarNumber","nVarValue","nVarDigits"],"nVarDigits":4,"nVarValue":0.1468}]},{"VariableValue":[{"nVarValue":0.4494,"tml_elements":["nVarNumber","nVarValue","nVarDigits"],"nVarDigits":4,"nVarNumber":1},{"nVarNumber":2,"tml_elements":["nVarNumber","nVarValue","nVarDigits"],"nVarDigits":4,"nVarValue":0.4059}],"tml_elements":["VariableValue","PropertyValue"],"PropertyValue":[{"nPropValue":-25.524,"CombinedUncertainty":{"tml_elements":["nCombUncertAssessNum","nCombExpandUncertValue"],"nCombExpandUncertValue":0.256,"nCombUncertAssessNum":1},"nPropNumber":1,"nPropDigits":5,"tml_elements":["nPropNumber","nPropValue","nPropDigits","CombinedUncertainty"]}]},{"VariableValue":[{"tml_elements":["nVarNumber","nVarValue","nVarDigits"],"nVarDigits":4,"nVarNumber":1,"nVarValue":0.4648},{"nVarDigits":4,"tml_elements":["nVarNumber","nVarValue","nVarDigits"],"nVarNumber":2,"nVarValue":0.2615}],"PropertyValue":[{"tml_elements":["nPropNumber","nPropValue","nPropDigits","CombinedUncertainty"],"nPropNumber":1,"nPropDigits":5,"nPropValue":-23.358,"CombinedUncertainty":{"nCombUncertAssessNum":1,"tml_elements":["nCombUncertAssessNum","nCombExpandUncertValue"],"nCombExpandUncertValue":0.235}}],"tml_elements":["VariableValue","PropertyValue"]},{"VariableValue":[{"nVarNumber":1,"nVarDigits":4,"tml_elements":["nVarNumber","nVarValue","nVarDigits"],"nVarValue":0.4653},{"nVarNumber":2,"nVarDigits":4,"tml_elements":["nVarNumber","nVarValue","nVarDigits"],"nVarValue":0.1425}],"tml_elements":["VariableValue","PropertyValue"],"PropertyValue":[{"tml_elements":["nPropNumber","nPropValue","nPropDigits","CombinedUncertainty"],"nPropDigits":5,"nPropNumber":1,"nPropValue":-20.068,"CombinedUncertainty":{"nCombUncertAssessNum":1,"nCombExpandUncertValue":0.202,"tml_elements":["nCombUncertAssessNum","nCombExpandUncertValue"]}}]},{"VariableValue":[{"nVarValue":0.4664,"nVarDigits":4,"tml_elements":["nVarNumber","nVarValue","nVarDigits"],"nVarNumber":1},{"nVarValue":0.3933,"nVarNumber":2,"nVarDigits":4,"tml_elements":["nVarNumber","nVarValue","nVarDigits"]}],"tml_elements":["VariableValue","PropertyValue"],"PropertyValue":[{"CombinedUncertainty":{"nCombUncertAssessNum":1,"nCombExpandUncertValue":0.264,"tml_elements":["nCombUncertAssessNum","nCombExpandUncertValue"]},"nPropValue":-26.329,"nPropDigits":5,"nPropNumber":1,"tml_elements":["nPropNumber","nPropValue","nPropDigits","CombinedUncertainty"]}]},{"tml_elements":["VariableValue","PropertyValue"],"PropertyValue":[{"tml_elements":["nPropNumber","nPropValue","nPropDigits","CombinedUncertainty"],"nPropNumber":1,"nPropDigits":5,"nPropValue":-20.504,"CombinedUncertainty":{"nCombExpandUncertValue":0.206,"tml_elements":["nCombUncertAssessNum","nCombExpandUncertValue"],"nCombUncertAssessNum":1}}],"VariableValue":[{"nVarValue":0.4807,"nVarDigits":4,"tml_elements":["nVarNumber","nVarValue","nVarDigits"],"nVarNumber":1},{"nVarDigits":4,"tml_elements":["nVarNumber","nVarValue","nVarDigits"],"nVarNumber":2,"nVarValue":0.1384}]},{"tml_elements":["VariableValue","PropertyValue"],"PropertyValue":[{"tml_elements":["nPropNumber","nPropValue","nPropDigits","CombinedUncertainty"],"nPropDigits":5,"nPropNumber":1,"CombinedUncertainty":{"nCombUncertAssessNum":1,"nCombExpandUncertValue":0.271,"tml_elements":["nCombUncertAssessNum","nCombExpandUncertValue"]},"nPropValue":-27.005}],"VariableValue":[{"tml_elements":["nVarNumber","nVarValue","nVarDigits"],"nVarDigits":4,"nVarNumber":1,"nVarValue":0.4825},{"nVarValue":0.3815,"nVarNumber":2,"tml_elements":["nVarNumber","nVarValue","nVarDigits"],"nVarDigits":4}]},{"VariableValue":[{"nVarNumber":1,"tml_elements":["nVarNumber","nVarValue","nVarDigits"],"nVarDigits":4,"nVarValue":0.4856},{"nVarNumber":2,"nVarDigits":4,"tml_elements":["nVarNumber","nVarValue","nVarDigits"],"nVarValue":0.2514}],"PropertyValue":[{"nPropValue":-24.326,"CombinedUncertainty":{"nCombUncertAssessNum":1,"nCombExpandUncertValue":0.244,"tml_elements":["nCombUncertAssessNum","nCombExpandUncertValue"]},"tml_elements":["nPropNumber","nPropValue","nPropDigits","CombinedUncertainty"],"nPropDigits":5,"nPropNumber":1}],"tml_elements":["VariableValue","PropertyValue"]},{"PropertyValue":[{"nPropValue":-20.897,"CombinedUncertainty":{"nCombUncertAssessNum":1,"nCombExpandUncertValue":0.21,"tml_elements":["nCombUncertAssessNum","nCombExpandUncertValue"]},"nPropDigits":5,"nPropNumber":1,"tml_elements":["nPropNumber","nPropValue","nPropDigits","CombinedUncertainty"]}],"tml_elements":["VariableValue","PropertyValue"],"VariableValue":[{"nVarNumber":1,"nVarDigits":4,"tml_elements":["nVarNumber","nVarValue","nVarDigits"],"nVarValue":0.4956},{"nVarValue":0.1344,"nVarDigits":4,"tml_elements":["nVarNumber","nVarValue","nVarDigits"],"nVarNumber":2}]},{"VariableValue":[{"nVarValue":0.4978,"tml_elements":["nVarNumber","nVarValue","nVarDigits"],"nVarDigits":4,"nVarNumber":1},{"tml_elements":["nVarNumber","nVarValue","nVarDigits"],"nVarDigits":4,"nVarNumber":2,"nVarValue":0.3702}],"tml_elements":["VariableValue","PropertyValue"],"PropertyValue":[{"CombinedUncertainty":{"nCombUncertAssessNum":1,"tml_elements":["nCombUncertAssessNum","nCombExpandUncertValue"],"nCombExpandUncertValue":0.277},"nPropValue":-27.64,"tml_elements":["nPropNumber","nPropValue","nPropDigits","CombinedUncertainty"],"nPropNumber":1,"nPropDigits":5}]},{"VariableValue":[{"nVarValue":0.5052,"nVarNumber":1,"tml_elements":["nVarNumber","nVarValue","nVarDigits"],"nVarDigits":4},{"nVarNumber":2,"tml_elements":["nVarNumber","nVarValue","nVarDigits"],"nVarDigits":4,"nVarValue":0.2418}],"tml_elements":["VariableValue","PropertyValue"],"PropertyValue":[{"nPropDigits":5,"nPropNumber":1,"tml_elements":["nPropNumber","nPropValue","nPropDigits","CombinedUncertainty"],"nPropValue":-24.961,"CombinedUncertainty":{"nCombExpandUncertValue":0.251,"tml_elements":["nCombUncertAssessNum","nCombExpandUncertValue"],"nCombUncertAssessNum":1}}]},{"PropertyValue":[{"CombinedUncertainty":{"nCombUncertAssessNum":1,"nCombExpandUncertValue":0.214,"tml_elements":["nCombUncertAssessNum","nCombExpandUncertValue"]},"nPropValue":-21.262,"tml_elements":["nPropNumber","nPropValue","nPropDigits","CombinedUncertainty"],"nPropDigits":5,"nPropNumber":1}],"tml_elements":["VariableValue","PropertyValue"],"VariableValue":[{"nVarValue":0.5098,"nVarNumber":1,"tml_elements":["nVarNumber","nVarValue","nVarDigits"],"nVarDigits":4},{"nVarNumber":2,"nVarDigits":4,"tml_elements":["nVarNumber","nVarValue","nVarDigits"],"nVarValue":0.1306}]},{"VariableValue":[{"nVarValue":0.5127,"nVarNumber":1,"tml_elements":["nVarNumber","nVarValue","nVarDigits"],"nVarDigits":4},{"nVarNumber":2,"tml_elements":["nVarNumber","nVarValue","nVarDigits"],"nVarDigits":4,"nVarValue":0.3592}],"tml_elements":["VariableValue","PropertyValue"],"PropertyValue":[{"nPropValue":-27.756,"CombinedUncertainty":{"tml_elements":["nCombUncertAssessNum","nCombExpandUncertValue"],"nCombExpandUncertValue":0.279,"nCombUncertAssessNum":1},"tml_elements":["nPropNumber","nPropValue","nPropDigits","CombinedUncertainty"],"nPropDigits":5,"nPropNumber":1}]},{"VariableValue":[{"nVarValue":0.5233,"tml_elements":["nVarNumber","nVarValue","nVarDigits"],"nVarDigits":4,"nVarNumber":1},{"nVarValue":0.2329,"nVarDigits":4,"tml_elements":["nVarNumber","nVarValue","nVarDigits"],"nVarNumber":2}],"tml_elements":["VariableValue","PropertyValue"],"PropertyValue":[{"nPropDigits":5,"nPropNumber":1,"tml_elements":["nPropNumber","nPropValue","nPropDigits","CombinedUncertainty"],"CombinedUncertainty":{"nCombUncertAssessNum":1,"tml_elements":["nCombUncertAssessNum","nCombExpandUncertValue"],"nCombExpandUncertValue":0.257},"nPropValue":-25.589}]},{"PropertyValue":[{"tml_elements":["nPropNumber","nPropValue","nPropDigits","CombinedUncertainty"],"nPropDigits":5,"nPropNumber":1,"nPropValue":-21.52,"CombinedUncertainty":{"nCombUncertAssessNum":1,"tml_elements":["nCombUncertAssessNum","nCombExpandUncertValue"],"nCombExpandUncertValue":0.216}}],"tml_elements":["VariableValue","PropertyValue"],"VariableValue":[{"nVarNumber":1,"tml_elements":["nVarNumber","nVarValue","nVarDigits"],"nVarDigits":4,"nVarValue":0.5236},{"nVarValue":0.127,"nVarNumber":2,"nVarDigits":4,"tml_elements":["nVarNumber","nVarValue","nVarDigits"]}]},{"tml_elements":["VariableValue","PropertyValue"],"PropertyValue":[{"CombinedUncertainty":{"tml_elements":["nCombUncertAssessNum","nCombExpandUncertValue"],"nCombExpandUncertValue":0.218,"nCombUncertAssessNum":1},"nPropValue":-21.659,"tml_elements":["nPropNumber","nPropValue","nPropDigits","CombinedUncertainty"],"nPropDigits":5,"nPropNumber":1}],"VariableValue":[{"nVarValue":0.5374,"nVarNumber":1,"nVarDigits":4,"tml_elements":["nVarNumber","nVarValue","nVarDigits"]},{"nVarValue":0.1233,"nVarNumber":2,"tml_elements":["nVarNumber","nVarValue","nVarDigits"],"nVarDigits":4}]},{"tml_elements":["VariableValue","PropertyValue"],"PropertyValue":[{"CombinedUncertainty":{"nCombExpandUncertValue":0.262,"tml_elements":["nCombUncertAssessNum","nCombExpandUncertValue"],"nCombUncertAssessNum":1},"nPropValue":-26.129,"nPropNumber":1,"nPropDigits":5,"tml_elements":["nPropNumber","nPropValue","nPropDigits","CombinedUncertainty"]}],"VariableValue":[{"nVarValue":0.5403,"nVarDigits":4,"tml_elements":["nVarNumber","nVarValue","nVarDigits"],"nVarNumber":1},{"nVarValue":0.2246,"nVarDigits":4,"tml_elements":["nVarNumber","nVarValue","nVarDigits"],"nVarNumber":2}]},{"PropertyValue":[{"nPropValue":-26.464,"CombinedUncertainty":{"nCombUncertAssessNum":1,"tml_elements":["nCombUncertAssessNum","nCombExpandUncertValue"],"nCombExpandUncertValue":0.266},"tml_elements":["nPropNumber","nPropValue","nPropDigits","CombinedUncertainty"],"nPropNumber":1,"nPropDigits":5}],"tml_elements":["VariableValue","PropertyValue"],"VariableValue":[{"nVarValue":0.5562,"nVarNumber":1,"nVarDigits":4,"tml_elements":["nVarNumber","nVarValue","nVarDigits"]},{"nVarValue":0.2168,"nVarNumber":2,"tml_elements":["nVarNumber","nVarValue","nVarDigits"],"nVarDigits":4}]},{"VariableValue":[{"nVarNumber":1,"nVarDigits":4,"tml_elements":["nVarNumber","nVarValue","nVarDigits"],"nVarValue":0.5713},{"nVarDigits":4,"tml_elements":["nVarNumber","nVarValue","nVarDigits"],"nVarNumber":2,"nVarValue":0.2094}],"PropertyValue":[{"CombinedUncertainty":{"tml_elements":["nCombUncertAssessNum","nCombExpandUncertValue"],"nCombExpandUncertValue":0.266,"nCombUncertAssessNum":1},"nPropValue":-26.467,"tml_elements":["nPropNumber","nPropValue","nPropDigits","CombinedUncertainty"],"nPropDigits":5,"nPropNumber":1}],"tml_elements":["VariableValue","PropertyValue"]},{"tml_elements":["VariableValue","PropertyValue"],"PropertyValue":[{"CombinedUncertainty":{"tml_elements":["nCombUncertAssessNum","nCombExpandUncertValue"],"nCombExpandUncertValue":0.266,"nCombUncertAssessNum":1},"nPropValue":-26.518,"tml_elements":["nPropNumber","nPropValue","nPropDigits","CombinedUncertainty"],"nPropNumber":1,"nPropDigits":5}],"VariableValue":[{"nVarNumber":1,"nVarDigits":4,"tml_elements":["nVarNumber","nVarValue","nVarDigits"],"nVarValue":0.5858},{"tml_elements":["nVarNumber","nVarValue","nVarDigits"],"nVarDigits":4,"nVarNumber":2,"nVarValue":0.2024}]},{"VariableValue":[{"nVarValue":0.5997,"tml_elements":["nVarNumber","nVarValue","nVarDigits"],"nVarDigits":4,"nVarNumber":1},{"nVarNumber":2,"nVarDigits":4,"tml_elements":["nVarNumber","nVarValue","nVarDigits"],"nVarValue":0.1956}],"PropertyValue":[{"nPropValue":-26.404,"CombinedUncertainty":{"nCombUncertAssessNum":1,"tml_elements":["nCombUncertAssessNum","nCombExpandUncertValue"],"nCombExpandUncertValue":0.265},"tml_elements":["nPropNumber","nPropValue","nPropDigits","CombinedUncertainty"],"nPropNumber":1,"nPropDigits":5}],"tml_elements":["VariableValue","PropertyValue"]},{"VariableValue":[{"nVarDigits":4,"tml_elements":["nVarNumber","nVarValue","nVarDigits"],"nVarNumber":1,"nVarValue":0.6132},{"nVarNumber":2,"tml_elements":["nVarNumber","nVarValue","nVarDigits"],"nVarDigits":4,"nVarValue":0.189}],"PropertyValue":[{"nPropValue":-26.095,"CombinedUncertainty":{"tml_elements":["nCombUncertAssessNum","nCombExpandUncertValue"],"nCombExpandUncertValue":0.262,"nCombUncertAssessNum":1},"tml_elements":["nPropNumber","nPropValue","nPropDigits","CombinedUncertainty"],"nPropDigits":5,"nPropNumber":1}],"tml_elements":["VariableValue","PropertyValue"]},{"tml_elements":["VariableValue","PropertyValue"],"PropertyValue":[{"CombinedUncertainty":{"tml_elements":["nCombUncertAssessNum","nCombExpandUncertValue"],"nCombExpandUncertValue":0.259,"nCombUncertAssessNum":1},"nPropValue":-25.76,"nPropNumber":1,"nPropDigits":5,"tml_elements":["nPropNumber","nPropValue","nPropDigits","CombinedUncertainty"]}],"VariableValue":[{"nVarValue":0.6267,"nVarNumber":1,"tml_elements":["nVarNumber","nVarValue","nVarDigits"],"nVarDigits":4},{"nVarDigits":4,"tml_elements":["nVarNumber","nVarValue","nVarDigits"],"nVarNumber":2,"nVarValue":0.1824}]},{"VariableValue":[{"nVarDigits":4,"tml_elements":["nVarNumber","nVarValue","nVarDigits"],"nVarNumber":1,"nVarValue":0.6394},{"nVarValue":0.1762,"nVarDigits":4,"tml_elements":["nVarNumber","nVarValue","nVarDigits"],"nVarNumber":2}],"tml_elements":["VariableValue","PropertyValue"],"PropertyValue":[{"tml_elements":["nPropNumber","nPropValue","nPropDigits","CombinedUncertainty"],"nPropNumber":1,"nPropDigits":5,"nPropValue":-25.449,"CombinedUncertainty":{"nCombExpandUncertValue":0.255,"tml_elements":["nCombUncertAssessNum","nCombExpandUncertValue"],"nCombUncertAssessNum":1}}]},{"VariableValue":[{"nVarValue":0.6517,"nVarNumber":1,"nVarDigits":4,"tml_elements":["nVarNumber","nVarValue","nVarDigits"]},{"nVarValue":0.1702,"nVarDigits":4,"tml_elements":["nVarNumber","nVarValue","nVarDigits"],"nVarNumber":2}],"PropertyValue":[{"nPropValue":-25.135,"CombinedUncertainty":{"tml_elements":["nCombUncertAssessNum","nCombExpandUncertValue"],"nCombExpandUncertValue":0.252,"nCombUncertAssessNum":1},"tml_elements":["nPropNumber","nPropValue","nPropDigits","CombinedUncertainty"],"nPropDigits":5,"nPropNumber":1}],"tml_elements":["VariableValue","PropertyValue"]}],"sCompiler":"TJP","nPureOrMixtureDataNumber":4,"dateDateAdded":"4/3/2012","Component":[{"nSampleNm":1,"RegNum":{"tml_elements":["nOrgNum"],"nOrgNum":1},"tml_elements":["RegNum","nSampleNm"]},{"tml_elements":["RegNum","nSampleNm"],"nSampleNm":1,"RegNum":{"nOrgNum":2,"tml_elements":["nOrgNum"]}},{"tml_elements":["RegNum","nSampleNm"],"nSampleNm":1,"RegNum":{"nOrgNum":3,"tml_elements":["nOrgNum"]}}],"PhaseID":[{"tml_elements":["ePhase"],"ePhase":"Liquid"}],"tml_elements":["nPureOrMixtureDataNumber","Component","eExpPurpose","sCompiler","sContributor","dateDateAdded","Property","PhaseID","Constraint","Variable","NumValues"],"Variable":[{"VariableID":{"RegNum":{"tml_elements":["nOrgNum"],"nOrgNum":1},"VariableType":{"eComponentComposition":"Mole fraction","tml_elements":["eComponentComposition"]},"tml_elements":["VariableType","RegNum"]},"nVarNumber":1,"VarPhaseID":{"eVarPhase":"Liquid","tml_elements":["eVarPhase"]},"tml_elements":["nVarNumber","VariableID","VarPhaseID"]},{"VariableID":{"VariableType":{"eComponentComposition":"Mole fraction","tml_elements":["eComponentComposition"]},"tml_elements":["VariableType","RegNum"],"RegNum":{"tml_elements":["nOrgNum"],"nOrgNum":3}},"nVarNumber":2,"VarPhaseID":{"eVarPhase":"Liquid","tml_elements":["eVarPhase"]},"tml_elements":["nVarNumber","VariableID","VarPhaseID"]}],"sContributor":"TRC","Constraint":[{"tml_elements":["nConstraintNumber","ConstraintID","ConstraintPhaseID","nConstraintValue","nConstrDigits"],"nConstraintValue":101,"ConstraintPhaseID":{"eConstraintPhase":"Liquid","tml_elements":["eConstraintPhase"]},"nConstrDigits":3,"nConstraintNumber":1,"ConstraintID":{"ConstraintType":{"ePressure":"Pressure, kPa","tml_elements":["ePressure"]},"tml_elements":["ConstraintType"]}},{"ConstraintID":{"tml_elements":["ConstraintType"],"ConstraintType":{"tml_elements":["eTemperature"],"eTemperature":"Temperature, K"}},"nConstraintNumber":2,"nConstrDigits":5,"ConstraintPhaseID":{"eConstraintPhase":"Liquid","tml_elements":["eConstraintPhase"]},"tml_elements":["nConstraintNumber","ConstraintID","ConstraintPhaseID","nConstraintValue","nConstrDigits"],"nConstraintValue":1273.2}]}],"tml_elements":["Version","Citation","Compound","PureOrMixtureData"],"Compound":[{"sStandardInChIKey":"PXHVJJICTQNCMI-UHFFFAOYSA-N","RegNum":{"nOrgNum":1,"tml_elements":["nOrgNum"]},"sStandardInChI":"InChI=1S/Ni","Sample":[{"nSampleNm":1,"eSource":"Commercial source","tml_elements":["nSampleNm","eSource","purity"],"purity":[{"eAnalMeth":["Not known"],"nPurityMass":99.99,"nStep":1,"tml_elements":["nStep","nPurityMass","nPurityMassDigits","eAnalMeth"],"nPurityMassDigits":4}]}],"sCommonName":["nickel","nickel element"],"tml_elements":["RegNum","sStandardInChI","sStandardInChIKey","sCommonName","sFormulaMolec","Sample"],"sFormulaMolec":"Ni"},{"sStandardInChI":"InChI=1S/Sn","RegNum":{"tml_elements":["nOrgNum"],"nOrgNum":2},"sStandardInChIKey":"ATJFFYVFTNAWJD-UHFFFAOYSA-N","sCommonName":["tin"],"tml_elements":["RegNum","sStandardInChI","sStandardInChIKey","sCommonName","sFormulaMolec","Sample"],"Sample":[{"nSampleNm":1,"eSource":"Commercial source","purity":[{"eAnalMeth":["Not known"],"nPurityMass":99.99,"nStep":1,"tml_elements":["nStep","nPurityMass","nPurityMassDigits","eAnalMeth"],"nPurityMassDigits":4}],"tml_elements":["nSampleNm","eSource","purity"]}],"sFormulaMolec":"Sn"},{"sStandardInChI":"InChI=1S/Sb","RegNum":{"nOrgNum":3,"tml_elements":["nOrgNum"]},"sStandardInChIKey":"WATWJIUSRGPENY-UHFFFAOYSA-N","Sample":[{"nSampleNm":1,"eSource":"Commercial source","purity":[{"nStep":1,"nPurityMassDigits":5,"tml_elements":["nStep","nPurityMass","nPurityMassDigits","eAnalMeth"],"eAnalMeth":["Not known"],"nPurityMass":99.999}],"tml_elements":["nSampleNm","eSource","purity"]}],"tml_elements":["RegNum","sStandardInChI","sStandardInChIKey","sCommonName","sFormulaMolec","Sample"],"sCommonName":["antimony"],"sFormulaMolec":"Sb"}],"THERMOML_MD5_CHECKSUM":"e167eb666d659906a481d41f7f5aec33"}